{"nupurino": "\ud83d\ude0d\ud83d\ude0d\ud83d\ude0d", "sxkshi__": "Wow", "rinu_sivaraman": "\ud83d\udc9c", "the_sohailshaikh": "Gorgeous girl", "kainth_hardeep": "\ud83d\udc4c\ud83d\udc4c", "_mr_im_the_boss_": "I want in", "mahzzzz": "saving me, for sure\ud83e\udd24\ud83d\udc98", "al_rockstr": "First u gotta save me", "manishapathania_": "Caption\ud83d\udd25", "chandanrawat176": "Women In Black Reloaded", "fredericourabat": "sauve toi", "browngirlgazin": "um??? what a pic???", "larry_t_hill": "\u270a\ud83c\udffe\u270a\ud83c\udffe\u270a\ud83c\udffe Goals, basically.", "369rastafaray": "\u2764\ufe0f\u2764\ufe0f hare Rama <3", "_shraddhadabral_": "OH MY GOD BLESSED\u2728\u2728", "jayadragon": "Call me beep me if you wanna reach me", "sneepies": "Yes \ud83e\udd29\ud83e\udd29\ud83e\udd29", "holly_ransom": "\u26a1\ufe0f\u26a1\ufe0f", "hossein.abre": "Hello, can you help my family? Can anyone help?", "tahsta": "Love the bottle green pants!!", "tonicrocanopix": "\ud835\udc47\u210e\ud835\udc56\ud835\udc60 \ud835\udc50\ud835\udc5c\ud835\udc5a\ud835\udc5a\ud835\udc52\ud835\udc5b\ud835\udc61 \u210e\ud835\udc4e\ud835\udc60 \ud835\udc4f\ud835\udc52\ud835\udc52\ud835\udc5b \ud835\udc50\ud835\udc52\ud835\udc5b\ud835\udc60\ud835\udc5c\ud835\udc5f\ud835\udc52\ud835\udc51 \ud835\udc51\ud835\udc62\ud835\udc52 \ud835\udc61\ud835\udc5c \ud835\udc38\ud835\udc62\ud835\udc5f\ud835\udc5c\ud835\udc5d\ud835\udc52\ud835\udc4e\ud835\udc5b \ud835\udc48\ud835\udc5b\ud835\udc56\ud835\udc5c\ud835\udc5b\u2019\ud835\udc60 \ud835\udc50\ud835\udc5c\ud835\udc5d\ud835\udc66\ud835\udc5f\ud835\udc56\ud835\udc54\u210e\ud835\udc61 \ud835\udc59\ud835\udc4e\ud835\udc64.", "manika.xoxo": "Aranya u inspire me and other teenage girls like me so much ,and thank you so much for all the things ur doing to save this world\ud83d\udc9e", "spri_huh": "Who are these *basic average girl* you are talking about and who is above average and below average thrn", "0reoluwa": "Lol Kim possible!", "kashastrophe": "this is giving me kim possible vibes", "theevocativewit": "\u2665\ufe0f\u2665\ufe0f\ud83d\udc4f\ud83d\udc4f", "ananyaakumarr": "thanks for blessing my eyes aranya i owe u one \u2764\ufe0f", "shsy_sings": "And I\u2019m in love", "_aksheri": "the energy we trying to have in 2019", "ayrasway": "Angaar hai angaar\ud83d\udd25\ud83d\udd25\ud83d\udd25", "mallikabasera": "Kim Possible \ud83d\udc97\ud83d\ude2d", "9_wolf_6": "Add me in the list of basic average boy who is going to save the word!\ud83d\ude4f", "shethnitul": "You are stronger than you believe. You have greater powers than you know", "sameeksheik": "sTRONG Kim Possible vibes", "vineethvincentofficial\nVerified": "Verified", "rohitvemp": "You can't stop me cuz I'm KIM POSSIBLE .\u2764\ufe0f\u2764\ufe0f\u2764\ufe0f\u2764\ufe0f", "raginimathur15": "\u2764\ufe0f", "advaita_gk": "Yass queen! \ud83d\udc51\u2764", "insane_insaan._": "Basic-ally, Hawt\u2764\ufe0f\ud83d\udd78\ufe0f", "oldhonewtricks": "Waifu please step on me you huge chunk of sunshiiiiiiiine \ud83d\ude0d\ud83d\ude0d\ud83d\ude0d\ud83d\ude0d\ud83d\ude0d\ud83d\ude0d", "phaseeh": "SERVE!", "tahamuls": "@sindhrella if that ain\u2019t you", "seeeeshells": "marry me", "ft.nishu": "\u2764\ufe0f\u2764\ufe0f", "shrushti.ashok": "REAL MOMMY", "asimbhatkar9983": "\ud83d\udd25\ud83d\ude0d\ud83d\ude0d", "antipravclub2.0": "Kim possible vibes !", "nitin.kashyap731": "Bohot hard\ud83d\ude0e"}