{"kojo415": "Hi", "alauddin_khan_0786": "Beautiful look", "sagnik.cr7": "\ud83d\ude0d\ud83d\ude0d\ud83d\ude0d\u2764\ufe0f\ud83d\udd25", "shanmugamsiva53": "I love you", "mourya8222": "Nice", "pasubhadra": "Osome \ud83d\ude0d", "minion00lover": "@moon004477", "simran.vats0404": "\ud83d\udc97Beautiful\ud83d\udc95\ud83d\udc95\ud83d\udc95", "vajidali2211": "Very nice", "axy.9387": "Wow Ur Smile is \ud83d\udcaf 9c...Very Lovely Smile... Always Keep it...\ud83c\uddee\ud83c\uddf3\ud83c\uddee\ud83c\uddf3\ud83d\ude4f\ud83d\ude4f", "just_kumail": "\ud83d\ude0d\ud83d\ude0d", "sushant_singh_ahlawat": "\ud83d\udc51", "krishxsolox1095": "Sexy", "anikketk": "Ki sundor", "sairaj442": "\ud83d\ude18\ud83d\ude18\ud83d\ude18\ud83d\ude18", "shahrukhfaizy_99": "\u2764\ufe0f", "kkk.1703": "\u2764\ufe0f", "__karma.believer": "\ud83d\ude0d\ud83d\ude18\ud83d\ude18", "mdash861": "Ur smile.... \u2764\ufe0f\u2764\ufe0f\u2764\ufe0f\u2764\ufe0f\u2764\ufe0f\u2764\ufe0f\u2764\ufe0f\u2764\ufe0f\u2764\ufe0f\u2764\ufe0f\u2764\ufe0f\u2764\ufe0f\u2764\ufe0f\u2764\ufe0f\u2764\ufe0f\u2764\ufe0f\u2764\ufe0f\u2764\ufe0f\u2764\ufe0f\u2764\ufe0f\u2764\ufe0f\u2764\ufe0f\u2764\ufe0f\u2764\ufe0f\u2764\ufe0f\u2764\ufe0f\u2764\ufe0f\u2764\ufe0f\u2764\ufe0f\u2764\ufe0f\u2764\ufe0f\u2764\ufe0f\u2764\ufe0f\u2764\ufe0f\u2764\ufe0f\u2764\ufe0f\u2764\ufe0f\u2764\ufe0f\u2764\ufe0f\u2764\ufe0f\u2764\ufe0f\u2764\ufe0f", "yashvaidhya": "Superb", "_md_abdullah_al_mamun": "I really \u2764\ufe0f you smile", "k.l.meriya": "Love you 3000", "kasish1448": "\u2764\ufe0f\u2764\ufe0f\u2764\ufe0f", "karmjeetbarman": "my favorite taapsee", "prominkabir": "\ud83d\udd25", "hiralpatel24": "\ud83d\ude18\ud83d\ude18\ud83d\ude18", "govindprasad3475": "Satya gunga ha", "moibebo": "Damn Pretty \u2665\ufe0f", "avaneesh35": "Chu", "cressydza": "Best picture ever", "iz_cie": "\ud83d\udc95\ud83d\udc95\ud83d\udc95", "shaikh_asif_iqbal2": "fetching...\ud83d\ude18", "adhesh.yadav": "(Calling)Ha Call Kyu kiya Bolla Tha Na Kbhi Call Mat Karna Ek Baat Nhi Hzaar Baat Bola Tha Yk Ek Baat Kahu Mai Bura Nhi Hu Bas Aapki Soch Achhi Nhi Nai Ek Chahat Thi Tere Sang jeene ki Varna Mohabat To Kisi Se Bhi Ho Skti Tbi Hazaro Chehro Mai Ek Tum Hi The jispe ham Mar Mite Varna Na Chahto ki Kmi Thi or Na Chahane Valo ki Yar Sala Maine So Baar Kaha Apne Dil se Chal Bhui Ja Use Pata Hai Har Baar Mere Dil Ne Kya Kaha Tum Dil Se Nhi Kahte Chlo Thik Hai Esa kro Agar Jana Hi Hai To Ruh Se Nikal Jao Rahi Baat Dol ki Use Ham Dekh Lenge OR AB TU JA Yaar Ja Sabse Jhagad Kar Tuje Apna Bnaya Tha Aakhir Mai Tu Vahi Nikali Jo Sabne Bataya Tha Par AB Mujhe Kuch Karna Hai Kuch Banna Hai Kuch Likhna Hai Kuch Kar Dikhana Hai SORRY Shayad Galti ho Gyi Mujhse OR Der Bhi Jaaa Dosto Kisi insan Ka Dil Tut Jaye OR Vo Sant Dimag Se Bethkar Positively Soche To Usme Unlimittd Energy Aa Jati Hai Jisse Vo Apne Carrier Ko Itni Uchai Tak Lk Ja Sakta Hai Jhan Se Log Uske Ek Ouiograph Ke Liye Tarsege Like Share \u00df Subscribe Insta ID MR Badshah-88 Avdhesh Premi Yadav sorry sorry sorry sorry sorry sorry...", "shoeshouse_7": "Koi meri gf banegi \ud83d\udc9e DM me", "pritishreeray": "\ud83d\ude0d\ud83d\ude0d\ud83d\ude0d\ud83d\ude0d", "jintudutt": "\u2764\ufe0f", "ji_gru": "\u0905\u092a\u0928\u0940 \u0915\u093f\u0938\u0940 \u092d\u0940 \u0938\u092e\u0938\u094d\u092f\u093e \u0915\u093e \u0938\u092e\u093e\u0927\u093e\u0928 \u0924\u0941\u0930\u0902\u0924 \u0915\u0930\u0935\u093e\u092f\u0947 \u0935\u094b \u092d\u0940 \u0918\u0930 \u092c\u0948\u0920\u0947 \u0924\u094b \u092b\u093f\u0930 \u0907\u0902\u0924\u091c\u093e\u0930 \u0915\u093f\u0938 \u092c\u093e\u0924 \u0915\u093e \u092c\u0938 1\u092b\u094b\u0928 \u0918\u0941\u092e\u093e\u0907\u090f \u0914\u0930 \u0905\u092a\u0928\u0940 \u0915\u093f\u0938\u0940 \u092d\u0940 \u0938\u092e\u0938\u094d\u092f\u093e \u0915\u093e \u0938\u092e\u093e\u0927\u093e\u0928 \u0924\u0941\u0930\u0902\u0924 \u092a\u093e\u092f\u0947.BEST INDIAN ASTROLOGER { 11 TIMES GOLD MEDALIST +91-9462163485 Get your love back Specialist Dispute in relationship, love breakup solution Husband- wife disturbance, Arrange marriage, Control Your Husband / Wife Under Your Hand Love problems solution , all problem solved only here.. mobile or what's no \ud83d\udc49+91-9462163485 \ud83d\udc48", "nemybhowmik": "\u2764\ufe0f\u2764\ufe0f\u2764\ufe0f\u2764\ufe0f\u2764\ufe0f\u2764\ufe0f\u2764\ufe0f\u2764\ufe0f\u2764\ufe0f\u2764\ufe0f\u2764\ufe0f\u2764\ufe0f\u2764\ufe0f\u2764\ufe0f", "veeramallick": "Taapsee ji aap mughe bhaut pasand ho mai aapka sare movie maine dekhi hai you are so pretty...... \u2764\ufe0f\u2764\ufe0f\u2764\ufe0f\u2764\ufe0f\u2764\ufe0f\u2764\ufe0f\u2764\ufe0f\u2764\ufe0f", "nabanil200": "Yea log hum jayso pa dhayen nehi deta ha .....I hate alllll accetors...but i love allll movie ....", "babluprajapat77": "\u2764\ufe0f\u2764\ufe0f\u2764\ufe0f\u2764\ufe0f", "dineshup45india": "i love you\u2764\ufe0f\ud83d\udd25", "umeshchandrabhardwaj": "\ud83d\ude0d\u2764\ufe0f", "jalexander2576": "Sweetheart", "pawandubey9381": "Wow", "sawansamrat6": "Aap to bollywood ki Queen ho love u mam", "shamsularifeenk": "Nice", "shunmuga72": "looking so pretty \u2764\ufe0f", "treetard6460": "Hey there Beautiful", "jot4231": "good", "krsh824": "Waaa", "shubhamsahu7659": "#gorgeous_looking", "matic.788": "incease your 5k insta followers for 999rs", "gurfatehsingharora": "\ud83d\udc4c\ud83d\udc4c\ud83d\udc93", "anand.agnihotri.1656": "Nice", "sunilkulria": "\ud83d\ude0d\ud83d\ude0d", "tanishqchandra1996": "Beautiful\u2764\ufe0f\u2764\ufe0f\u2764\ufe0f\u2764\ufe0f", "saurabh_machikar": "Love u \ud83d\ude18\ud83d\ude18\ud83d\ude18\ud83d\ude18\ud83d\ude18", "_a_v_d_e_s_h_": "Nice pic hot tappsee", "tm.tota": "\ud83d\ude0d\ud83d\ude0d\ud83d\ude0d\ud83d\ude0d\ud83d\ude0d\ud83d\ude0d\ud83d\ude18\ud83d\ude18\ud83d\ude18\ud83d\ude18\ud83d\ude18\ud83d\ude18\ud83d\ude18", "chatse.rahul": "Osm", "ankur_nalhera_gujjar": "Tera tood ni\ud83c\udfac\ud83c\udfac\ud83c\udfac\ud83c\udfac\ud83c\udf4e", "shahe767": "Hello", "j.k.siva": "\ud83d\ude0dqA", "bheemsinghdhariwal": "\ud83d\udd25\ud83d\udd25\ud83d\udd25\ud83d\udd25\ud83d\udd25\u2764\ufe0f\u2764\ufe0f\u2764\ufe0f\u2764\ufe0f\u2764\ufe0f\u2764\ufe0f", "naveed7116": "So nice", "hashmi.zishan": "Mai tera haye re jabra fan ho gaya beautiful smile \ud83d\ude0d", "amitratnaparkhii": "\u2764\ufe0f\u2764\ufe0f\u2764\ufe0f", "aukhan2670": "So Beautiful\ud83d\ude0d", "naughty.jessica69": "Follow @hotness.overloaded69 for latest hot content #hotnessoverloaded", "gurdishk62": "Cute pic \ud83d\udca5\ud83d\udc4d\ud83d\udc90\u2665\ufe0f\ud83c\udf38\ud83e\udd8b\ud83e\udd8b\ud83e\udd8b\ud83e\udd8b", "aru.rinky": "Beautiful \u2763\ufe0f", "devil_bealert": "\u2764\ufe0flovely", "ishaan.rana.752": "Bad profile of yours doesn't exist.", "yangfokhandu": "Lady Fighter...lookin gr8\ud83d\udc98\ud83d\udc98\ud83d\udc98", "rayyan.sageer1988": "Lovely", "mahendrabbc": "\u2764\ufe0f\u2764\ufe0fhot sexy", "unconquerable_arighna": "\ud83d\ude0d\ud83d\ude0d\ud83d\ude0d\u2764\ufe0f\u2764\ufe0f", "naeemqureshi6792": "Quit", "_hitu77_": "\ud83d\ude0d", "sparklerfarhaan": "Mashallah", "vikash_sersiya": "Best precious pic of cuet taapsee....\ud83d\ude0d\ud83d\ude0d\ud83d\ude0d\ud83d\ude0d\ud83d\udc97\ud83d\udc97\ud83d\udc97\ud83d\ude18\ud83d\ude18", "prati804": "I just love ur hair..and ur innocence", "sachinsinha08": "Osam", "vineetbanga2": "Hello taapsee, hey? HruGod bless u 1", "rg23281": "Baby !", "pooja420goswami": "All the best for your upcoming movie bull eye's \ud83d\udc03\ud83d\udc03", "ashmita_singhania_": "Asome", "anjalimaurya6371": "Haye ladki\ud83d\ude48", "sindhi_akbar_soomro": "Beauty, love from sindhies\u2764", "rishi_jd780": "So cool", "pratik_dokphode": "Nice click", "deshmukh6823": "100 paika 100", "g.o.k.u__sun": "Gorgeous\ud83d\ude0d\ud83d\ude0d\ud83d\ude0d", "akanksharatna": "Ur smile is very cute \ud83d\ude18\ud83d\ude0d", "deepakshah734": "I l u", "_saroj__prabhu_": "Nice\ud83d\udc4d", "atulrajput139": "\ud83d\udc91\u2698\u2698\u2698\u2698\u2698", "anilkapoor82": "Beautiful", "chottu453": "Gorgeous beautiful. Looking pretty. \ud83d\udc8b\ud83d\udc8b\ud83d\udc8b\ud83d\udc8b\ud83d\udc8b\ud83d\udc8b\ud83d\udc8b\ud83d\udc8b\ud83d\udc8b\ud83d\udc8b\ud83d\udc8b\ud83d\udc8b\ud83d\udc8b\ud83d\udc8b\ud83d\udc8b\ud83d\udc8b\ud83d\udc8b\ud83d\udc8b\ud83d\udc8b\ud83d\udc8b\ud83d\udc8b\ud83d\udc8b\ud83d\udc8b\ud83d\udc8b\ud83d\udc8b\ud83d\udc8b\ud83d\udc8b\ud83d\udc8b\ud83d\udc8b\ud83d\udc8b\ud83d\udc8b\ud83d\udc8b\ud83d\udc8b\ud83d\udc8b\ud83d\udc8b\ud83d\udc8b\ud83d\udc8b\ud83d\udc8b\ud83d\udc8b\ud83d\udc8b\ud83d\udc8b\ud83d\udc8b\ud83d\udc8b\ud83d\udc8b\ud83d\udc8b\ud83d\udc8b\ud83d\udc8b\ud83d\udc8b\ud83d\udc8b\ud83d\udc8b\ud83d\udc8b\ud83d\udc8b\ud83d\udc8b\ud83d\udc8b\ud83d\udc8b\ud83d\udc8b\ud83d\udc8b\ud83d\udc8b\ud83d\udc8b\ud83d\udc8b\ud83d\udc8b\ud83d\udc8b\ud83d\udc8b\ud83d\udc8b\ud83d\udc8b\ud83d\udc8b\ud83d\udc8b\ud83d\udc8b\ud83d\udc8b\ud83d\udc8b\ud83d\udc8b\ud83d\udc8b\ud83d\udc8b\ud83d\udc8b\ud83d\udc8b\ud83d\udc8b\ud83d\udc8b\ud83d\udc8b\ud83d\udc98\ud83d\udc96\ud83d\udc95\ud83d\udc95\ud83d\udc94\ud83d\udc93\u2764\u2764\ud83d\udc97\ud83d\udc9d\ud83d\udc9e\ud83d\udc9f\u2763\ufe0f", "devenghone": "nice \ud83d\udc4c", "eu.gene8075": "\u2764\ufe0f\u2764\ufe0f\u2764\ufe0f", "taapseee143": "\u2764\ufe0f\u2764\ufe0f\u2764\ufe0f", "siddhesh.shende": "\ud83d\udcaf\ud83d\udcaf\ud83d\udc4d", "manishajoshisharma": "\ud83d\udd25", "itishivi20": "So beautiful\ud83d\ude0d\ud83d\ude0d", "dakshkundra2": "Beautiful", "sandaybujji": "\ud83d\ude0d\ud83d\ude0d\ud83d\ude0d\ud83d\ude0d\ud83d\ude0d\ud83d\ude0d\ud83d\ude0d", "nsdeo652019": "Internal beauty do not need external outfits to beautify.", "ranbir8855": "dramatic ,cinematic smile", "bankar8810": "Real talent with beauty", "vanshika_4048": "Cutieeeeee\ud83d\ude0d\ud83d\ude0d", "navi3656": "Looking hot", "aanammansoori": "\ud83d\ude0d\ud83d\ude0d\ud83d\ude0d So nice pic\u2764\ufe0f\u2764\ufe0f\u2764\ufe0f", "nazimkhan249": "U are my favorite", "funky922420": "mtv troll jaise fake show se publicity paa kr star bngyi...", "preity_maurya_official_": "Beautiful", "dashingboyrickyy": "My love \ud83d\ude0d", "aziz.fatima.9619": "\u2764\ufe0f", "ardra_ramesh": "@akshay_puthiya_veetil enth look analle ivalk.", "maarsh_mellow_qween": "Kya awesome look he yaar apki\ud83d\udd25\ud83d\udd25\ud83d\udd25\ud83d\udd25", "ishani_singh_484": "So sweet", "perdeepwadhwa": "Hello", "serajhave": "\u2764\ufe0f\u2764\ufe0f\u2764\ufe0f", "kr_jeevan_singh_solanki": "Big fan of u mam.. u are real queen of bollywood.. #Diehardfan\ud83d\ude0a", "_yoursayan_": "love you \ud83d\ude0d\ud83d\ude0d\ud83d\ude0d\ud83d\ude0d\ud83d\ude0d", "divyasharma11554": "\ud83d\udd25\ud83d\udd25\ud83d\udd25", "klpuneet79": "\ud83d\ude0d\ud83d\ude0d\ud83d\ude0d\ud83d\ude0d\ud83d\ude0d\ud83d\ude0d", "mamtajangidcat": "Always fresh", "harunbashashaik6446": "Soon our meet our embracy dear dear dear", "monarishisingh": "\ud83d\ude18", "wasimshah1376": "\u2764\ufe0f\u2764\ufe0f\u2764\ufe0f", "abhijeetsalunkhe9696": "\ud83d\udc4f\ud83d\udc4f\ud83d\udc4f\ud83d\udc4c\ud83d\udc4c\ud83d\udc4c\ud83d\udc4f\ud83d\udc4f\ud83d\udc4f\ud83d\ude1c\ud83c\udf1f\ud83d\udcaa\ud83d\udd1d\ud83d\udd25\u270c\ud83d\udc78", "nikitajain7746": "\ud83d\ude0d\ud83d\udc99", "gawali605": "Hi", "aashikabisht_28": "Beautiful\ud83d\ude0d", "ritu.sanare": "\u2764\ufe0f", "madushan__f.do": "\ud83d\udc97\ud83d\udc97\ud83d\udc97\ud83d\udc97\ud83d\udc97", "maxwelblaze": "\u2764\u2764\u2764", "100msandeepsinghrajput": "I love you mam", "nitinsaini.0583": "i am ur big fan \ud83d\udc4c\ud83d\udc4c\ud83d\udc4c\ud83d\ude0d\ud83d\ude0d\ud83d\ude0d\ud83d\udc8b\ud83d\udc8b\ud83d\udc8b\ud83d\udc8b\ud83d\ude18\ud83d\ude18\ud83d\ude18\ud83d\ude18\ud83d\ude18\ud83d\udc98\ud83d\udc98\ud83d\udc98\ud83d\udc9e\ud83d\udc9e\ud83d\udc9e\ud83d\udc9e\ud83d\udc97\ud83d\udc97", "love_lust_relationships": "Hey guys follow me for couples posts and awesome pics \ud83d\udd1e\ud83d\udd1e @love_lust_relationships @love_lust_relationships @love_lust_relationships", "prince3osker": "Qutiiii", "jafar_h_odedara_4": "Super", "sidharthmalhotrakingdom": "Beautiful \ud83d\ude0d\ud83d\ude0d\ud83d\ude0d\u2764\ufe0f", "jainhema87": "Kya aap bachpan se itni cute or khubsurat h mam", "wiseseaweeed": "Stunning Marvelous beautiful gorgeous pretty amazing breathtaking", "lahurathod_fc": "\ud83d\ude18\ud83d\ude18\u2764\ufe0f", "raghav_shinge": "\ud83d\ude0d\ud83d\ude0d\ud83d\ude0d\ud83d\ude18\ud83d\ude18\ud83d\ude18\ud83d\ude18", "vnvrma": "Woww\u2764\ufe0f\u2764\ufe0f\u2764\ufe0f", "__.martin.kathuria__": "NYC \u2764\ufe0f\u2764\ufe0f", "najimakhatun_143": "\u2764\ufe0f", "raviboykumar": "\u2764\ufe0f\ud83d\udd25\ud83d\udd25", "vipingupta314": "Love you dear", "0.mohit": "\u2764\ufe0f", "zednunisa_": "\ud83d\ude0d\ud83d\udd25", "drx_rohit_kumar": "Adorable\ud83d\ude0d\ud83d\ude0d\ud83d\ude0d\ud83d\ude0d\ud83d\udc4c\ud83d\ude18\ud83d\ude18", "kirtiwarshubham": "Superb\ud83d\udc4c\ud83d\udc4c", "the_heart_robber_sai": "\u2764\ufe0f", "bae_ur_luv": "\ud83d\udd34\ud83d\udd34\ud83d\udd34\ud83d\udd34\ud83d\udd34\ud83d\udd34\ud83d\udd34\ud83d\udd34\ud83d\udd34\ud83d\udd34 visit my page I'm having great stuff !!! \ud83d\udc9a Just give me a bit of support \u2764 content by arpitasinghrajpoot \u2763 \ud83d\udd34\ud83d\udd34\ud83d\udd34\ud83d\udd34\ud83d\udd34\ud83d\udd34\ud83d\udd34\ud83d\udd34\ud83d\udd34\ud83d\udd34", "premkashyap48": "\u2764\ufe0f\u2764\ufe0f", "sandipshah4064": "Beautiful", "pancham_journey": "I love u", "vickymasun": "\u2764\ufe0f\u2764\ufe0f\u2764\ufe0f", "mr._vivek____26": "Every pic is super na\ud83d\ude02\ud83d\ude02\ud83d\ude02\ud83d\ude02", "spoorthy_shashidhar": "\ud83d\ude0d\ud83d\ude0d", "shayna_khan_a074": "\ud83d\ude0d\ud83d\ude0d\ud83d\ude0d\ud83d\ude0d", "souravranjan1092": "hey sexy", "sunit320": "Very nice \ud83d\udc4c \ud83d\udc4c \u2764\ufe0f", "piyali7890": "\ud83d\ude0d", "sadhana_vyapu": "Gorgeous...", "jinalpatel_6": "@imp_malay bhabhi \ud83d\ude1d\u2764", "pintumandal2050": "Love you Tapsee", "rahul_kothale": "\u2764\ufe0f\u2764\ufe0f\u2764\ufe0f\u2764\ufe0f\u2764\ufe0f\u2764\ufe0f", "tausif_pathan5747": "wow", "rishisaagar": "Love you \u2764\ufe0f\u2764\ufe0f", "nish__sen": "Really you looking like Madhuri mam \ud83d\ude0d love you @tapsee143 mam", "girl.icon99": "Wow di\ud83d\udc4c\ud83d\udc4c", "official_raman_33": "\ud83d\udd25\ud83d\udd25\ud83d\udd25", "subhashyadav.yadav.182940": "\u2764\ufe0fi\u2764\ufe0fl\u2764\ufe0fu\u2764\ufe0f", "shradhatomar14": "Gorgeous\ud83d\ude18\ud83d\ude18", "soonaebee": "The wanna be\ud83d\udc0d\ud83d\udc0d\ud83d\udc0d\ud83d\udc0d\ud83d\udc0d", "nazneensheikh7": "\u2665\ufe0f\ud83d\ude18\u2665\ufe0f", "sangeetamaden": "\ud83d\ude02", "avanishinns": "Beautiful\ud83d\ude0d\ud83d\udc95", "alok3138": "\ud83d\udd25\ud83d\udd25\ud83d\udc4c\ud83d\udc4c\ud83d\udc4c\ud83d\udd25\ud83d\udd25", "ay.esha2987": "Y", "avtar8957": "Nyc", "sam_surve_official": "On dance diwane set\ud83d\ude0d\ud83d\ude0d\ud83d\ude18", "sand7kr": "Smile more...!!", "sameer.patankar.94": "Gorgeous", "kittu.rathore.946": "\ud83d\udc93\ud83d\udc93\ud83d\udc95", "akashghosh93": "Hi Beautiful....\ud83d\udc4c\ud83d\udc4c\ud83d\udc4c\ud83d\udc4c\ud83e\udd1a", "_diksha__rana__": "\ud83d\udd25\ud83d\udd25\ud83d\udd25", "na_sir_k": "Cutie", "dewang.ajmera": "looking Damm cool \ud83d\udd25", "bukulbala": "PRETTY", "vijayalaxmirn": "Beautiful", "vsa_61": "World's most beautiful and lovely and sweet and pleasant personality.. My B' day is also 1 St August.", "vikasdisel": "Queen sirf Ada se \ud83d\udca5\ud83d\udca5\ud83d\udca5\ud83d\udca5", "darsh_landge": "I am love with this look of u taapsee\ud83d\ude0d", "chandramanigoel": "Tum itni beautiful kyu ho yaar......", "mondolrekha": "Cute\ud83d\ude07", "wajidjavedabdul": "\ud83d\ude18", "sahil_sanga_": "I love you taapsee\ud83d\ude0d", "vfx_abhijeet": "When camera suddenly comes to you..& u have to hide ur tombacco...\ud83d\udc4f", "nizamuddin1740": "Beautifull mam", "imranbalwa": "\u2764\ufe0f", "me_sumit_kumar": "Oh god , m going mad for u", "sharmiaboni": "\ud83d\udc95", "rajasekar361987": "Always good looking", "nevilledhabhar": "So pretty.. Keep that smile going.. God Bless\ud83e\udd17", "holidayplaner": "Plan your vacation with us", "samim_hoshang": "Love\u2764\ufe0f\ud83d\ude18", "a_m_i_t_d_a_y_m_a": "Awesome\ud83d\ude18\ud83d\ude18\ud83d\ude18\ud83d\ude18", "waseemahmedkhanshab6951": "Gbn", "shrividhyasadhna": "\ud83d\ude0d\ud83d\ude0d\ud83d\ude18\ud83d\ude18", "dushyant.yadav.961": "2nd name of beauty Taapsee\ud83d\udc4c", "niedp": "Sooo delectable..petite..elegant..", "md.ejaz6": "O supper se upper", "akshayseth_oo7": "Beautiful", "vidhi_20012": "Hii", "rk.rishi7081": "Nyc picture click but this picture not shoot th profile....\ud83d\udc96\ud83d\udc96\ud83d\udc96\ud83d\udc96\ud83d\udc96\ud83d\udc96\ud83d\udc96\ud83d\udc96\ud83d\udc96\ud83d\udc96\ud83d\udc96", "bijaybhor": "\ud83d\udc4c\ud83d\udc4c\ud83d\udc4c\ud83d\udc4c", "terabhaiadii": "Itni khush kyu ho", "satya_s_mohanty": "Crushhhh !!! \ud83d\ude0d\ud83d\ude0d\ud83d\ude0d\ud83d\ude0d", "tekri_sarkar_guna_666": "\ud83d\ude0d\ud83d\udd25\ud83d\udd25\ud83d\udd25", "deepnarayan_khatait": "\ud83d\ude0d\ud83d\ude0d", "satpalbhullar89": "So much beautiful\u2764\ufe0f\u2764\ufe0f\u2764\ufe0f\u2764\ufe0f\u2764\ufe0f\u2764\ufe0f", "i_aninditakhanra": "\ud83d\udd25\ud83d\udd25\ud83d\udd25\ud83d\udd25\ud83d\udd25\ud83d\udd25\ud83d\udd25\ud83d\udd25", "makansumit": "Nice \ud83d\udc4c Mam", "hirenjoshi983": "So Beautiful pic", "msg4u.abhi": "Ishq \u0939\u094b \u091c\u093e\u090f\u0917\u093e bhainsss \u0915\u0940 tangggg \ud83d\ude48", "aditaygondaliya": "\u2764\ufe0f", "2tarfaa_talks": "Just check out my content and follow if u like it.", "alisherjamote": "Cute", "luckygoswam8": "Soooooooo soooooooo very very beautiful", "omprakshjamuar2016": "Pink girl", "yogesh15nov": "Cute\u2764\ufe0f", "rashmibisht0880": "Tooooo \ud83d\udd25\ud83d\udd25\ud83d\udd25\u2764\ufe0f", "neerajbisht1212": "Smile Badi Soni ha", "yashvspute": "Looking\u0915\u0921\u0915", "swagsajid": "Very beautiful\u2764\ufe0f\u2764\ufe0f\u2764\ufe0f\u2764\ufe0f", "lucky998765": "I love you my bestii \ud83d\ude0d\ud83d\ude0d", "i_am_sachin_powar_": "Cool looking nice pic \ud83d\ude18\ud83d\ude18\ud83d\ude18\u2764\u2764\u2764\u2764", "nx_t_dude": "Superb\ud83d\ude0b", "agrawal.himanshu26": "Kya baat hai! Bahut khoobsoorat! Mashaallah!", "manampilly_ajay": "\ud83d\ude0d\ud83d\ude0d", "onkarchandra": "Cute looking", "sabrin_nahar_armin": "wow", "krishnakumarbhatiya": "\u2764\ufe0f\u0905\u0924\u093f\u0938\u0941\u0928\u094d\u0926\u0930\u2764\ufe0f", "ankit.7087": "You r looking so pretty", "nasir_faria": "\u2764\ufe0f\u2764\ufe0f\u2764\ufe0f\u2764\ufe0f\u2764\ufe0f\u2764\ufe0f\u2764\ufe0f\u2764\ufe0f\u2764\ufe0f\u2764\ufe0f\u2764\ufe0f\u2764\ufe0f\u2764\ufe0f\u2764\ufe0f", "abhayjainssho": "\ud83d\ude0dhi baby", "vinodchauhan00": "\u2764\u2764\u2764\u2764\u2764\u2764\u2764\u2764", "lahot.vikas": "\u2764\ufe0f\u2764\ufe0f\u2764\ufe0f", "chandanknocking": "Very cute", "multani9005": "Both profile roxx... Jatti", "arif_alazaam": "One of the best beautiful & talented actress of Bollywood..", "navrajjawandha": "Oh man", "mshsadi": "I\u2764\ufe0f\u2764\ufe0f\u2764\ufe0f\u2764\ufe0f\u2764\ufe0fu", "m.faizan86": "@taapsee I am hoping the finger is not your middle finger \ud83d\ude00", "rk49993": "Wow Gorgeous\u2764\ufe0f\u2764\ufe0f", "haaffy": "\u2665\ufe0f", "kirpal_navi": "\ud83d\udc95\ud83d\udc95\ud83d\udc95\ud83d\udc95", "hkng_andrew_ng_wai_khong": "Hello", "vikram813213": "\ud83d\udc4c\ud83d\udc4c\ud83d\udc4c\ud83d\udc4c\ud83d\udc4c", "mongeeese": "Follow @skitsandwiggles for the FULL video \ud83d\ude33\ud83d\ude00 - @skitsandwiggles", "muhammadyunus229": "Masha Allah", "ayyse_nurr1": "Beautiful girl \u2764\ufe0f", "manojraja74841": "Hi.my.dear.very cute.\u2764\ufe0f\u2764\ufe0f\u2764\ufe0f\u2764\ufe0f", "shabnur16": "So beautiful you\ud83d\udc9d\ud83d\udda4\ud83d\udda4\ud83d\udda4\ud83d\udda4\u2764\u2764\ud83d\udc95\u2763\u2763\ud83d\udc9d\ud83d\udc9d\ud83d\udc9d\ud83d\udc9d\ud83d\udda4\ud83d\udda4\ud83d\udda4\ud83d\ude18", "khaildk9": "\ud83d\udc95\ud83d\udc95\ud83d\udc95\ud83d\udc95\u2764\ufe0f", "canvas_of_moyee": "Smile\u2764\ufe0f\u2764\ufe0f\ud83d\udc4c\u2764\ufe0f\u2764\ufe0f\u2764\ufe0f\u2764\ufe0f\u2764\ufe0f\u2764\ufe0f\ud83d\udc4d\u2764\ufe0f\u2764\ufe0f\ud83d\udc4c\u2764\ufe0f\u2764\ufe0f\u2764\ufe0f\u2764\ufe0f\u2764\ufe0f\ud83d\udc4d\u2764\ufe0f\u2764\ufe0f\u2764\ufe0f\u2764\ufe0f\u2764\ufe0f\u2764\ufe0f\u2764\ufe0f\u2764\ufe0f\ud83d\udc4c", "rohittulankar": "Khubsurati\ud83d\ude0d\u2764\ufe0f", "abrar_pathan786": "\u2665\ufe0f\u2665\ufe0f\u2665\ufe0f\u2665\ufe0f\u2665\ufe0f\u2665\ufe0f\u2665\ufe0f\u2665\ufe0f\u2665\ufe0f\u2665\ufe0f\u2665\ufe0f", "v_i_s_h_u___thakur": "\ud83d\ude0d", "ou___ss__ama_": "\ud83d\ude0d\ud83d\udc4f", "riyankhan5523": "Nice", "ar_7dreams": "Rhythm Divine \ud83c\udf20\ud83d\udd1d", "bindu_karra": "Boyishness", "zeemore02": "Whattttttt\ud83d\udd25\ud83d\udd25\ud83d\udd25\ud83d\udd25\ud83d\udd25\ud83d\ude0d\ud83d\ude0d\ud83d\ude0d\ud83d\ude0d\ud83d\ude0d", "awasthi1927": "Tapsu", "aamtipu": "\u2764\ufe0f", "farhan_0009": "Beautiful flowers", "theanitabella": "\ud83d\ude0d", "_its_vijay__": "\ud83d\udda4\ud83d\udda4", "mdimran1569": "Love you", "debabratabond77": "Nice smile", "fur3908": "Wow kaha se li \ud83d\udc57", "vickythakur709": "Super", "chetankumar8693": "\ud83d\udc4c\ud83d\udc4c\ud83d\udc4c\ud83d\udc4c\u2764\ufe0f\u2764\ufe0f\ud83d\udc4d\ud83d\udc4d#chetankumar8693", "rohit.chandra.503": "Lovely", "just._.aif143": "Pretty..\ud83d\ude0d\ud83d\ude0d", "jayshri750": "yeah re .. \u2764\ufe0f actuly left angel se tumhari nose tedhi lagti hai i think ha after saw all pics so this angel or frount angel is perfect \ud83d\ude0d\ud83e\udd29", "_syed_arbas_": "\ud83d\udc90\ud83d\udc90\ud83d\udc90\ud83d\udc90\ud83d\udc90\ud83d\udc90\u2764\ufe0f\u2764\ufe0f", "saumyakomer": "All tym ft frvt\ud83d\ude0d", "rohansweet777": "Hot \ud83d\udd25 and Sweet \ud83c\udf39", "gulshan.gour.12": "Love you yr", "kunal0324": "Any profile would look good with that smile\ud83d\ude18\ud83d\ude18\ud83d\ude18", "djraj25": "Suppa profile.", "ishratarai19": "These people have nothing to do with the country... Just posinh and being mouth shut for any comment.... How can they be Indians if they don't speak for Indian's welfare...", "rajesh_rakholiya": "@taapsee amazing design looks pretty", "savntlalit": "\ud83d\udc9a", "kolewadmahadev": "Looking \u2764\ufe0fgorgeous \ud83d\ude0d", "shubamjaiswal1888": "Kaim", "somyasinghal11": "Ma\u2019am looked soo pretty today \ud83d\ude0d", "nehakumari3224": "\ud83d\ude0d\ud83d\ude0d\ud83d\ude0d\ud83d\ude0d\ud83d\ude0d", "aadarsh_meh": "A beatiful turn by a beautiful princess", "azam_immu": "\ud83d\udd25", "s.v9rajput": "Wwwwwoooowwww", "ilyas_ghediri": "We love you", "mukul_jangid00": "Looking so beautiful.....", "itz__haris": "U r so prtty", "hotlinesneaks": "You beautyyy! \u2764\ufe0f\ud83d\ude0d", "ariyan_chowdhury_sohan": "\u2764\ufe0f\u2764\ufe0f", "ravishing_17": "\ud83d\ude0d\ud83d\ude0d\ud83d\ude0d\u2764\ufe0f\u2764\ufe0f", "swapyawesome": "Adorable cute smile looking so beautiful", "harsh35745": "Nice photo \ud83d\udd25", "el.professora7": "U r so beautiful \ud83d\ude0d\u2764\ufe0f", "ravindersound": "Dam cute @taapsee \ud83c\udf39\ud83d\ude0a", "shahidrajput0707": "Beautiful", "tiger_sattar_khan_chayal": "Beautiful \u2764\ufe0f\ud83d\ude0d modl..", "nipundas16": "\u2764\ufe0f\u2764\ufe0f\ud83d\udc4c\ud83d\udc4c", "mayuri__92": "I m girl but I love you \u2764\ufe0f\u2764\ufe0f\u2764\ufe0f\u2764\ufe0f\u2764\ufe0f\u2764\ufe0f\u2764\ufe0f\u2764\ufe0f\u2764\ufe0f\ud83d\ude18\ud83d\ude18\ud83d\ude18\ud83d\ude18\ud83d\ude18", "mayyank_jaain": "Looking a bit like madhuri D", "azim79464": "Nice\ud83d\udd25\ud83d\udd25\ud83d\udd25", "rahulsinghharsvardhan": "Looking hot", "hs.lohith": "\u2764\ufe0f", "shth_hrn": "\u0aae\u0aa8\u0ac7 \u0ab2\u0abe\u0a97\u0acd\u0aaf\u0ac1\u0a82 \u0aab\u0abe\u0a82\u0a95\u0ac0 \u0aac\u0aa8\u0abe\u0ab5\u0ac7 \u0a9b\u0ac7.. \u0aab\u0acb\u0a9f\u0abe\u0aae\u0abe\u0a82..", "anjalipalny": "\ud83d\udd25\ud83d\udd25", "hri_06_": "Awesomeness overloaded \ud83d\ude09", "prabhjotsingh.prab.35": "\u2764\ufe0f\u2764\ufe0f\u2764\ufe0f\u2764\ufe0f\u2764\ufe0f\u2764\ufe0f\u2764\ufe0f\u2764\ufe0f\u2764\ufe0f\u2764\ufe0f\u2764\ufe0f\u2764\ufe0f\u2764\ufe0f\u2764\ufe0f\u2764\ufe0f\u2764\ufe0f\u2764\ufe0f\u2764\ufe0f\u2764\ufe0f\u2764\ufe0f\u2764\ufe0f\u2764\ufe0f\ud83d\udc93\ud83d\udc93\ud83d\udc93\ud83d\udc93\ud83d\udc93", "zoya_2_6": "\ud83d\ude0d\ud83d\ude0d\ud83d\ude0d\ud83d\udc4c", "abinavgupta": "\u2764\ufe0f", "hardly_gangster": "my cutie mam and my fev star but reply nhi dete \ud83d\ude14\ud83d\ude14", "_akkuuu._": "Prettiest \u2764\ufe0f", "meet_chouhan89": "\ud83d\ude18\ud83d\ude18\ud83d\ude18", "rakesh.lakhotia.9": "Khoobsurat h tu itna kha nhi jata", "nadia76.83": "https://youtu.be/n4B3BujnG1o", "guinrituparna": "Good looking \ud83d\udc4c\ud83d\udc4c\ud83d\udc4c\ud83d\udc4c\ud83d\udc4c", "__.siimmii.__": "\ud83d\ude0d\u2764\ufe0f", "dhage_rudra": "Wow nice\ud83d\udc4c\u2764\ufe0f\ud83d\ude18\ud83d\udc4c", "navneetgolecha": "Luv u tappu\ud83d\ude18\ud83d\ude0d\u2764\ufe0f", "amisraty": "\u2764\ufe0f\u2764\ufe0f\u2764\ufe0f", "trupti_sahoo97": "Beautiful \ud83d\ude0d", "desai.madhukar": "Lovely\ud83d\udc4f\ud83d\udc4f\ud83c\udf1f\ud83c\udf1f\ud83c\udf1f\ud83c\udf1f", "mohdnadeem1702": "nice ptofile\ud83d\udd25\ud83d\udd25", "shivanii0701": "\ud83d\udc95", "a_lysosome": "\u2764\ufe0f", "sameer_a02": "\u2705\u2705\u2705", "neev8288": "\ud83d\udc4c", "anil.doliya.92": "\ud83d\udc9e\ud83d\udc9e\ud83d\udc9e", "tarun_5060": "Cutie\ud83d\ude18\ud83d\ude0d", "rajiv21908": "\ud83d\ude0d\ud83d\udc95\ud83d\ude0d\ud83d\udc95", "oo7jitender": "\u2764\ufe0f\u2764\ufe0f\u2764\ufe0f\u2764\ufe0f\u2764\ufe0f\u2764\ufe0f\u2764\ufe0f\u2764\ufe0f", "saifulislam.sayed.520": "\u2764\ufe0f\u2764\ufe0f\u2764\ufe0f\u2764\ufe0f", "itzbong_": "Yeh chudi ears mai kon pehenta h bhai\ud83d\ude02\ud83d\ude02", "yash.pandey.102977": "You are super", "addytie": "U just smile \u2764\ufe0f sare pose acche lagne lagtey Hain...", "rishabhjaiswar": "U r so adorable @taapsee \u2764\ufe0f\u2764\ufe0f\u2764\ufe0f\u2764\ufe0f\ud83d\ude18", "nikesh9411": "Soooooooo sweet\u2763\ufe0f\ud83d\ude0d\ud83d\ude31", "0mii_10": "\u2764\ufe0f\u2764\ufe0f\u2764\ufe0f\u2764\ufe0f\u2764\ufe0f", "solanki.kaushik.1029": "\ud83d\udc4cbeautiful\ud83d\udc4c", "sandeepsharma015": "Khatrnak \ud83d\udc4c\ud83d\ude18", "handcraftkurtis": "\u2764\ufe0f\u2764\ufe0f\u2764\ufe0f\u2764\ufe0f\u2764\ufe0f\u2764\ufe0f\u2764\ufe0f\u2764\ufe0f\u2764\ufe0f", "saurabhsrivastava4685": "Sometimes u suits the profile....vise e versa..", "dimple_samuckcham": "Beautiful \ud83d\udc96", "_a_r_ju_": "Any profile Suits You the best \u2764\ufe0f", "raunak_mahato": "You soooo preety \ud83d\udd25\ud83d\ude0d\ud83d\ude0d\ud83d\ude0d\ud83d\ude0d", "cutiepie_oyshe": "Onek sundor lagtese\ud83d\ude0d", "ashu_reddii": "\u2764\ufe0f\u2764\ufe0f", "sumeetsharma2020": "\u2764\ufe0f\u2764\ufe0f", "krishma99s": "Elegant \ud83d\ude0d", "_blackitude.___": "\ud83d\ude0d\ud83d\udd25", "nandinijaiswal.30": "\ud83e\udd29\ud83e\udd29", "mdkaif0402": "Beautifull", "raghumanchal": "Very nice", "sairaj__09": "\u2764\ufe0f\u2764\ufe0f\ud83d\udc8b\ud83d\udc8b\ud83d\udc8b\ud83d\udc8b\ud83d\udc8b\ud83d\udc8b\ud83d\udc8b\ud83d\ude18\ud83d\ude18", "shyamtiwari42": "Nice one tp ji", "karthika_cuteyy": "\u2665\ufe0f\u2665\ufe0f", "madhushukla45": "So cute \ud83d\udc4c", "maharshahbaz35": "Yr tum kitni achi ho\u2764\ufe0f", "_angel_sush__": "I like you Taapsee", "mayaali_mannu": "Love From Pak\ud83d\ude0d", "devaresatish": "\ud83d\udc4c\ud83d\udc4c\ud83d\udc4c\ud83d\udc4c\ud83d\udc4c\u2764\ufe0f\u2764\ufe0f\u2764\ufe0f\u2764\ufe0f\u2764\ufe0f\u2764\ufe0f\u2764\ufe0fbeautiful \ud83d\udc51\ud83d\udc4c\ud83d\udc4c\ud83d\udc4c\ud83d\udc4c\u2764\ufe0f\u2764\ufe0f\u2764\ufe0f", "chnaveen89": "\u2764\ufe0f", "krishnan17": "\ud83c\udf39\ud83c\udf39\ud83c\udf39", "iam_comrade7": "Lovely baby\ud83d\ude0d\u2764\ufe0f\u2764\ufe0f\u2764\ufe0f\ud83d\udd25", "d_garwal": "\u2764\ufe0fSweet Hart\u2764\ufe0f", "thakur_yogesh_03": "So pretty", "maruthi_reddy_mr": "\ud83d\ude18", "shaneoemac": "#canyouhelpmechallenge", "salmani8828": "Masaallaha", "osamaessakhan": "\u2764\ufe0f\u2764\ufe0f\u2764\ufe0f\u2764\ufe0f\u2764\ufe0f\u2764\ufe0f\u2764\ufe0f\u2764\ufe0f\u2764\ufe0f\u2764\ufe0f\u2764\ufe0f", "akshitakataria09": "\ud83d\ude0d\ud83d\ude0d\ud83d\ude0d\ud83d\ude0d\ud83d\ude0d", "beingamaankhan1036": "\ud83d\ude0d\ud83d\ude0d\ud83d\ude0d\ud83d\ude0d\ud83d\ude0d\ud83d\ude0d", "samo._.sy_": "\ud83d\ude0d\ud83d\ude0d", "satyendrashah0750": "Beautiful \ud83d\udd25\ud83d\udd25\ud83d\udd25", "akshayvs1794": "\ud83d\ude0d", "saurabh.897": "\ud83d\ude0d\ud83d\ude0d\ud83d\ude0d\ud83d\ude0d\ud83d\ude0d\ud83d\ude0d\ud83d\ude0d\ud83d\ude0d\ud83d\ude0d\ud83d\ude0d\ud83d\ude0d\ud83d\ude0d\ud83d\ude0d\ud83d\ude0d\ud83d\ude0d\ud83d\ude0d\ud83d\ude0d\ud83d\ude0d\ud83d\ude0d\ud83d\ude0d\ud83d\ude0d\ud83d\ude0d\ud83d\ude0d\ud83d\ude0d\ud83d\ude0d\ud83d\udd25\ud83d\udd25\ud83d\udd25\ud83d\udd25", "viper37_": "Nice one \ud83d\ude0a", "parmodkumar119": "Dadi ke haal tere\ud83d\ude02\ud83d\ude02\ud83d\ude02\ud83d\ude02@taapsee", "thakkarhiteshsota": "\ud83d\ude0d\ud83d\ude0d\ud83d\ude18\ud83d\ude0a\ud83d\udc4c\ud83e\udd17", "prasanth_mps_kumar": "\u2764\ufe0f\u2764\ufe0f", "dk0977": "Awesome", "sanam_akhri": "Ok", "_mahi_515": "\ud83d\udc99\ud83d\udc99\ud83d\udc99", "vijayj.4599": "\u2763\ufe0f\u2763\ufe0f", "gopalvikram": "That's an amazing one, \ud83d\udc4c\ud83d\udc4d\ud83d\ude0d", "pophaleanil": "P\ud83d\udc4c\ud83e\udd17\ud83d\ude0d\ud83d\ude0d\ud83d\udc4d", "ankurkothari6": "Gorgeous", "anarkoli13": "\ud83d\udc9c\ud83d\udc9c\ud83d\udc9c\ud83d\udc9c\ud83d\udc9c", "mankarshital": "\ud83d\udc95\ud83d\ude18\ud83d\udc9a\u2764\ufe0f\ud83d\udc9b", "sultan786raj": "Awesome \ud83c\udf39", "vishaljaiswal59": "Oooosssmm mam\ud83d\udc4c\ud83d\udc4c", "goyalkashish": "Very nice", "from_b_to_i": "\ud83d\udc96\ud83d\udc96\ud83d\udc96\ud83d\udc96\ud83d\udc96", "shirode_akash8542": "Lovely @taapsee", "shubham_golya_jat": "Any profile is good on you", "rajeshpoplani": "Eligant look", "karuna1557": "You are beautiful.Please change your DP which looks like Micheal Jackson", "priyanka_s2": "Gorgeous!", "beingb_____": "I love you tapsee\u2764\ufe0f\ud83d\ude0d", "whatsyourrashi_": "Gorgeousssssss\ud83d\ude0d\ud83d\ude0d\ud83d\ude0d\ud83d\ude0d\ud83d\ude0d", "ranineelam1122": "\ud83d\udc97\ud83d\udc97\ud83d\udc97", "sonainamalik.007": "Nice", "shwetaforfun": "\ud83d\ude0d\ud83d\ude0d\ud83d\ude0d\u2764\ufe0f\u2764\ufe0f\u2764\ufe0f", "pannu3991": "\u2764\ufe0f\u2764\ufe0f", "kinshuk581": "Lovely", "reddy0747": "I thought that u use all-out", "thakor__akash__inf__1919": "Nice", "mehreen_mery": "Innocent People everyday are brutally killed in kashmir ..please rais your voice ..humanity comes first #freeKASHMIR", "aarav_rroy": "\ud83d\ude0d\ud83d\ude0d\ud83d\ude0d", "sachin.kumar170277": "Beautiful \ud83d\udc93\ud83d\udc93\ud83d\udc4d\ud83d\udc4d\ud83d\udc4d", "janvi_patel_110": "\ud83d\udd25\ud83d\udd25\ud83d\udd25", "healingflower9": "\ud83d\udc95\ud83d\udc95\ud83d\udc95\ud83d\ude0d", "_sa_nah___": "\ud83e\udd40\ud83e\udd40\u2764\ufe0f", "roka.jyoti": "Absolutely perfect", "amitkartik": "Oye hoye zaalim\u2764\ufe0f", "mukkuu____": "Smile \ud83c\udf39\ud83d\udd25\ud83d\ude0a\u2728\ud83d\udc4c\ud83c\udf41", "ngananya1298": "Beauty", "majidsageer": "Gorgeous", "akrk18": "True indeed !", "_natural_beauty_2020": "\ud83d\ude0d\ud83d\ude0d\ud83d\ude0d\ud83d\ude0d\ud83d\ude0d", "sandeep.jangid.7758235": "Congrats for mission mangal....", "abdullaansari587": "nice photo", "ankit.saharan.3701": "\ud83e\udd18\ud83d\ude4f\ud83d\udc4f", "rd_0211": "Thats an amazing click!! You have a striking resemblance to Preity Zinta in this pic.", "jayveeruikey": "Gajab", "er_shan_20": "Very nice looking", "sonu_rana1777770": "\ud83d\udc4c\u2764\ufe0f\u2764\ufe0f\u2764\ufe0f", "gag5172": "\u2764\ufe0f", "world_famous_astrologer_india": "God bless you Taapsee you are an amazing actress .\ud83d\udc4d", "anuj_taunk_28": "WOW", "sumittiwariofficial": "Lo aaj mai kahta hu..... I \u2764\ufe0f u @taapsee", "justsanyam_2000": "\u2764\ufe0f\ud83d\ude0d\u2764\ufe0f\u2764\ufe0f\ud83d\ude0d\u2764\ufe0f\ud83d\ude0d\u2764\ufe0f\ud83d\ude18", "thankimilank": "\u2764\ufe0f\u2764\ufe0f", "its_race_till_the_hell": "One of the most sweetest actress met In my life", "sudipmphoto": "\ud83d\udc4c\ud83d\udc4c", "ummanood8": "J", "the_amanpatel": "\ud83d\ude0d\ud83d\ude0d\ud83d\ude0d\ud83d\ude0d\ud83d\ude0d\ud83d\ude0d\ud83d\ude0d\ud83d\ude0d", "amitkishor23": "\ud83d\udd25\ud83d\udd25\ud83d\udc4d\ud83d\udc4c\ud83d\udc4f\ud83d\ude18\ud83d\ude18\ud83d\ude18\u2764\ufe0f\u2764\ufe0f\u2764\ufe0f\u2764\ufe0f looking so lovely", "harishnag17": "Mud mud k na dekh...mud mud k...", "wardas.gallery": "You pretty and strong women\ud83d\ude0d", "parwej.ansari.33483": "Beautiful", "___xenomancy": "That smile..that damn smile\u2764", "lightqueen_jrs2502": "Ur smile is soo cute\u2665\ufe0f\u2764\ufe0f", "alisha54khan": "\ud83d\udd25\ud83d\udd25\ud83d\udd25\ud83d\udd25", "altaf.alishah.3323": "Super \u2764\ufe0f\u2764\ufe0f\u2764\ufe0f\ud83d\ude0d", "v.k.07._": "\ud83d\udd25\ud83d\udd25\ud83d\udd25\ud83d\udd25\ud83d\udd25\ud83d\udd25\ud83d\udd25\ud83d\udd25\ud83d\ude18\ud83d\ude18\ud83d\ude18\ud83d\ude18\ud83d\ude18\ud83d\ude18\ud83d\ude18\ud83d\ude18\ud83d\ude18\ud83d\ude0d\ud83d\ude0d\ud83d\ude0d\ud83d\ude0d\ud83d\ude0d\ud83d\ude0d\ud83d\ude0d\ud83d\ude0d", "astrologer_ashutosh_maharaaj": "\u0927\u094b\u0916\u093e \u0928\u0939\u0940\u0902 \u092a\u0915\u094d\u0915\u093e \u0935\u093e\u0926\u093e \u0915\u0939\u0940\u0902 \u0928\u093e \u0939\u094b \u0915\u093e\u092e \u0939\u092e\u0938\u0947 \u0932\u094b \u0938\u092e\u093e\u0927\u093e\u0928 \u092a\u0902\u0921\u093f\u0924 \u091c\u0940 \u0906\u091a\u093e\u0930\u094d\u092f (\u092e\u093e\u0924\u093e \u092e\u0939\u093e\u0915\u093e\u0932\u0940 \u0909\u092a\u093e\u0938\u0915) \u0939\u0930 \u0938\u092e\u0938\u094d\u092f\u093e \u0915\u093e \u0938\u092e\u093e\u0927\u093e\u0928 (101/,\u0917\u093e\u0930\u0902\u091f\u0940 )\"\u0938\u0947 \u0915\u093f\u092f\u093e \u091c\u093e\u0924\u093e \u0939\u0948 (WhatsApp number:+9175682-66302)= \u0938\u092e\u0938\u094d\u092f\u093e \u0915\u0948\u0938\u0940 \u092d\u0940 \u0939\u094b \u091c\u0921\u093c \u0938\u0947 \u0916\u0924\u094d\u092e =\u091c\u0948\u0938\u0947 (\u0932\u0935 \u092e\u0948\u0930\u093f\u091c)= (\u0935\u0936\u0940\u0915\u0930\u0923 )=\u0917\u0943\u0939 \u0915\u094d\u0932\u0947\u0936 \u0935\u093f\u0926\u0947\u0936 \u092f\u093e\u0924\u094d\u0930\u093e (\u092a\u0924\u093f \u092a\u0924\u094d\u0928\u0940 \u092e\u0947\u0902 \u0905\u0928\u092c\u0928) \u0915\u093e\u0930\u094b\u092c\u093e\u0930 \u092e\u0947\u0902 \u0918\u093e\u091f\u093e \u0938\u0902\u0924\u093e\u0928 \u0939\u094b\u0928\u093e \u092f\u093e \u0939\u094b\u0915\u0930 \u0928\u0937\u094d\u091f \u0939\u094b \u091c\u093e\u0928\u093e Naukri me promosan =\u092a\u0922\u093c\u093e\u0908 \u092e\u0947\u0902 \u092e\u0928 \u0928\u093e \u0932\u0917\u0928\u093e (\u092a\u094d\u092f\u093e\u0930 \u092e\u0947\u0902 \u0927\u094b\u0916\u093e) \u0917\u0943\u0939 \u0915\u094d\u0932\u0947\u0936 \u0938\u094c\u0924\u0928 \u0926\u0941\u0936\u094d\u092e\u0928 \u091b\u0941\u091f\u0915\u093e\u0930\u093e =\u092d\u0942\u092e\u093f \u0926\u094b\u0937 \u092a\u093f\u0924\u094d\u0930 \u0926\u094b\u0937 \u0915\u093e\u0932\u0938\u0930\u094d\u092a \u0926\u094b\u0937 =\u092e\u093e\u0902\u0917\u0932\u093f\u0915 \u0926\u094b\u0937 \u0928\u0935\u0917\u094d\u0930\u0939 \u092a\u0942\u091c\u093e \u092a\u093e\u0920 \u0939\u092e\u093e\u0930\u093e \u0915\u093e\u092e \u0939\u0935\u0928 \u092a\u0942\u091c\u093e \u092a\u093e\u0920 \u0915\u0947 \u0926\u094d\u0935\u093e\u0930\u093e \u0939\u0930 \u0938\u092e\u0938\u094d\u092f\u093e \u0915\u093e \u0938\u092e\u093e\u0927\u093e\u0928 \u0935\u093f\u0927\u093f \u092a\u094d\u0930\u0942\u092b \u0915\u093f\u092f\u093e \u091c\u093e\u0924\u093e \u0939\u0948 \u092d\u091f\u0915\u0947 \u0939\u0941\u090f \u0932\u0949\u0915 \u090f\u0915 \u092c\u093e\u0930 \u091c\u0930\u0942\u0930 \u0938\u0947\u0935\u093e \u0915\u093e \u092e\u094c\u0915\u093e \u0926\u0947\u0902 mobile number :(+91-75682-66302)\ud83d\ude4c", "nainagupta60": "\ud83d\udd25", "mahto6332": "Happy friendsipday\u2764\ufe0f", "lalawmpuii_88": "Sooo beautiful\ud83d\ude0d\ud83d\ude18", "_baba_ji_ke_memes_": "\ud83d\udd25\ud83d\udc4f\u2764\ufe0f\ud83d\ude4c\ud83d\ude0d\ud83d\ude2eAmazing Click \ud83d\udd25\ud83d\udc4f\u2764\ufe0f\ud83d\ude4c\ud83d\ude0d\ud83d\ude2e@taapsee", "gaurav_dildostiect": "Beautiful looking \u0924\u093e\u092a\u0938\u0940 \ud83d\udc95", "razzaq__jan": "\u27a4 #\ud835\ude51\ud835\ude40\ud835\ude4d\ud835\ude54_\ud835\ude49\ud835\ude44\ud835\ude3e\ud835\ude40 \u27a4\ud83c\udf3a\ud83c\udf43\ud83c\udf3a\u2500\u27a4.", "ersahiljadon": "U looks good always...", "water7365": "You are one of a kind in the bestie category$$$$$$$$$", "nanolya_anil_kumar": "\ud83d\udc4c\ud83d\udc4c", "busy_buddiiiii_ms": "\ud83d\ude0d", "kiingsslayer": "\u2764\ufe0f\u2764\ufe0f\u2764\ufe0f", "bani_6661": "\ud83d\ude0d", "anil.d.dabhi.7": "Nice \ud83d\udc4c \ud83d\udc4c\ud83d\udc4c\ud83d\udc4c\ud83d\udc4c", "klasnobl": "\u2764\ufe0f", "2011dhillon_jasbir": "she is so natural ...", "_.sneha_.singh_": "\u2764\ufe0f\u2764\ufe0f\u2764\ufe0f", "muskan____110": "\u2665\ufe0f\u2665\ufe0f\u2665\ufe0f\u2665\ufe0f\u2665\ufe0f\u2665\ufe0f", "ganeshgani.b.79": "Very smart taapsee", "vidhyaramnishad": "NYC,\ud83d\udc4f\u2764\ufe0f\ud83d\ude02", "vishalkr852": "Waah kya baat kya baat", "408blackrose": "\ud83d\ude05\ud83d\ude05\ud83d\ude05", "pranabborah669": "Hi", "priyyaaaaaa__": "Omgggg my girlcrush\u2764\ud83d\ude18\ud83d\ude18\ud83d\ude18\ud83c\udf0f", "6_6_69sm": "Wow butifulnice", "nishita.negii": "Speechless \ud83d\udc4c\ud83d\udd25", "zaheer_ahmad2600": "Kanhaiya ki Girl @ Taapsee Aapsi\ud83d\udc4f. And fascination level \ud83d\udcaf", "dkrajchaudhary": "Aap bahut cute ho", "vik_pnchl": "\u2764\ufe0f\u2764\ufe0f\u2764\ufe0f", "filmy.look": "Daily updates on Bollywood Breaking News only on \ud83d\udc49 @filmy.look", "chiraag_v5.e": "\ud83d\ude18\ud83d\ude18\ud83d\ude18\ud83d\udc4c", "yamcheetri": "\u2764\ufe0f\ud83d\ude0b", "thedevotedbanana": "That smile... Never seen you like this. A very welcome change in you, beautiful.", "indian.gag": "\ud83d\ude0d\ud83d\ude0d\ud83d\ude0d\ud83d\ude18\ud83d\ude18", "munnu_ku": "\ud83d\ude0d\ud83d\ude0d\ud83d\ude0d\ud83d\ude18\ud83d\ude18\ud83d\udc4c", "rajbirkaur76": "Wow!!", "marutiprabhakargaikwad": "Mast figar\u2764\ufe0f\ud83d\ude0d\ud83d\udd25", "_vidya_balan_fc": "Cuteee \ud83d\ude0d\ud83d\ude0d\ud83d\ude0d", "snehabloom": "\ud83d\ude3b\ud83d\ude3b\ud83d\ude3b\ud83d\ude3b", "lkyadav061": "Lovely \ud83d\ude18\ud83d\udd25\ud83d\ude0d", "butter___fingers": "\ud83d\udc9c\ud83d\udc9c\ud83d\udc9c\ud83d\ude0d\ud83d\ude0d\ud83d\ude0d\ud83d\ude18\ud83d\ude18\ud83d\ude18", "1_0_0_rabh_1_4_3": "\ud83d\ude0d\ud83d\ude09\ud83d\ude31", "jitendr7902": "Biutiful", "sandy18481": "Waaaoww\ud83d\ude0d\ud83d\udc95", "krishan.gautam.31": "Looking so pretty\ud83d\udc93\ud83d\udc93\ud83d\udc93\ud83d\udc93\ud83d\udc93\ud83d\udc93\ud83d\udc93\ud83d\udd25\ud83d\udd25\ud83d\udd25\ud83d\udd25\ud83d\udd25", "aparna1969_01": "Beautiful", "nisarkhan91104gmail.com8": "Beautiful", "nivritiiii": "\ud83d\ude18\ud83d\ude18\ud83d\ude18\ud83d\ude18\ud83d\ude18love youuuuu doll", "jamwallion_n_i_t_e_s_h_93": "Soooo soooo adorable\u2764\ufe0f", "imsamstarboy": "Okay ...the truth is @team_kangana_ranaut sucks ... she deserves this \ud83d\udc49\ud83d\udc4b\ud83d\udc4b\ud83d\udc4b", "soam_1310": "\ud83d\udd25\ud83d\udd25\ud83d\udd25", "bhavin_maisuriya_2000": "Lookong so Gorgeous \ud83d\udc95\ud83d\udc95\ud83d\udc95", "rahulsinghr441": "\ud83d\ude0d\ud83d\ude0d\ud83d\ude0d\ud83d\ude0d", "sachin_sonawane_4141": "Im your big big biggest fan mam plzz 1 reply me\ud83d\ude18\ud83d\ude18\ud83d\ude18\ud83d\ude18\ud83d\ude18", "avi_vinay": "\ud83d\ude0d", "823preet": "\ud83d\ude0d\ud83d\ude0d\ud83d\ude0d\u2764\ufe0f", "shah_re_yaar": "\ud83d\udc96\ud83d\udc96\ud83d\udc8b\ud83d\ude18", "prangon_b_rozario": "\u2764", "patel.ikram.007": "Nice pic", "sa_njay1318": "\u2764\ufe0f\u2764\ufe0f\u2764\ufe0f\u2764\ufe0f\u2764\ufe0f\u2764\ufe0f", "babushayansaeed": "\ud83d\udc9d", "jagdish.chawla.127": "Wow", "manavchaudhary08": "@taapsee \ud83d\udd25\ud83d\udd25\u2764\ufe0f", "machine.350": "Our love never ends for you madam. Reply to the comman man it keeps us still alive", "krishnaja.99": "\ud83d\ude18\ud83d\ude18", "mohanshr__": "\ud83d\ude0d\ud83d\ude0d\ud83d\ude0d\ud83d\ude0d\ud83d\ude0d\ud83d\ude0d\ud83d\ude0d\ud83d\ude0d\ud83d\ude0d\ud83d\ude0d\ud83d\ude0d\ud83d\ude0d\ud83d\ude0d\ud83d\ude0d\ud83d\ude0d\ud83d\ude0d\ud83d\ude0d\ud83d\ude0d\ud83d\ude0d\ud83d\ude0d\ud83d\ude0d\ud83d\ude0d\ud83d\ude0d\ud83d\ude0d \ud83d\ude18\ud83d\ude18\ud83d\ude18\ud83d\ude18\ud83d\ude18\ud83d\ude18\ud83d\ude18\ud83d\ude18\ud83d\ude18\ud83d\ude18\ud83d\ude18\ud83d\ude18\ud83d\ude18\ud83d\ude18\ud83d\ude18\ud83d\ude18\ud83d\ude18\ud83d\ude18\ud83d\ude18\ud83d\ude18\ud83d\ude18\ud83d\ude18\ud83d\ude18\ud83d\ude18\ud83d\ude18\ud83d\ude18\ud83d\ude18\ud83d\ude18\ud83d\ude18\ud83d\ude18\ud83d\ude18\ud83d\ude0d\ud83d\ude0d\ud83d\ude0d\ud83d\ude0d\ud83d\ude0d\ud83d\ude0d\ud83d\ude0d\ud83d\ude0d\ud83d\ude0d\ud83d\ude0d\ud83d\ude0d\ud83d\ude0d\ud83d\ude0d\ud83d\ude0d\ud83d\ude0d\ud83d\ude0d\ud83d\ude0d\ud83d\ude0d\ud83d\ude0d\ud83d\ude0d\ud83d\ude0d\ud83d\ude0d\ud83d\ude0d\ud83d\ude0d\ud83d\ude0d\ud83d\ude0d\ud83d\ude0d\ud83d\ude0d\ud83d\ude0d\ud83d\ude0d\ud83d\ude0d\ud83d\ude0d", "kaynaatagrawal": "lovee\ud83d\udd25\ud83d\udd25", "krndhaliwal": "\u2764\ufe0f\u2764\ufe0f\u2764\ufe0f\u2764\ufe0f\u2764\ufe0f\u2764\ufe0f\u2764\ufe0f\u2764\ufe0f\u2764\ufe0f\u2764\ufe0f", "darshan_aulakh\nVerified": "Verified", "sivaaye_shiv": "\ud83d\udc97", "devendraprajapati52312": "Marry pray my modiji", "abhinavsharma6878": "Mera yakeen krna akhri mohbbt ho tm meri!! Aage to bs ab samjhote hnge \u2764\ufe0f lots of love God bless u keep shining", "suman_smk_": "@basaulaganesh yo vaiya ne kam chalauthiea milaidinu 400 rupaiya dinxu 100 rch haldinxu", "savalakhiyayogesh": "Jakassssssssssssss\u00dfsssssssssssssss\u00dfsssss", "karan_debabrata": "naughty girl\ud83d\udc02", "vehle_yaar5444": "\ud83d\ude0d\ud83d\ude0d", "anjalisarmamrk123": "Jdfm", "fmwdotcom": "You look fabulous", "akhil.xz": "Tambakoo kha rhi ho ka baccha", "a.k.h.i.l_09_": "\u2764\ufe0f\u2764\ufe0f", "jasleen_berry": "Wow", "aasoolbi": "\ud83d\udc4f\ud83d\udc4f\ud83d\udc4f\ud83d\udc4f", "sahib_aman143": "Nice", "harpalsing1313": "\u2764\ufe0f", "jyotipasi_": "\ud83d\ude18\ud83d\ude18\ud83d\ude18\ud83d\ude18\ud83d\ude18\ud83d\ude18", "lovely.dia9": "\ud83d\ude0d\ud83d\ude0d\ud83d\ude0d\ud83d\ude0d\ud83d\ude0d", "23everydaythoughts97": "Hey , please checkout my page i hope you would like it and please follow me if you liked the posts \ud83d\ude0a thanks and yeah you are amazing \u2764\ufe0f\u2764\ufe0f\u2764\ufe0f\u2764\ufe0f\u2764\ufe0f\u2764\ufe0f\u2764\ufe0f\u2764\ufe0f\u2764\ufe0f\u2764\ufe0f\ud83d\ude48\ud83d\ude48@23everydaythoughts97 @23everydaythoughts97 @23everydaythoughts97.", "therealanup8583": "\ud83d\ude0d", "vickypyaarx": "haayeeee stunninggggg\ud83d\ude2d\ud83d\udc9e", "sukriti_sharma6": "\u2764\ufe0f", "sarvaiyayogirajsinh7916": "U beauty\ud83d\udd25\ud83d\udc9e", "saniyanarwal": "\ud83d\ude0d\ud83d\ude0d\u2764\u2764\u2764\u2728\u2728\u2728", "karsannaykkarsannayk": "Cute.smaile.and.lovely", "sid.gawai": "\u2764\ufe0f love you", "___teddy______": "Love you babe", "gaurav.borade": "Osm\ud83d\ude0d", "mahi_sharma_24": "\ud83d\udd25\ud83d\udd25\ud83d\udd25\ud83d\ude0d\ud83d\ude0d", "dineshkapoor1706": "hi Tapsee....im a big fan of you....you are very sweet..Love you dear", "abhishek5528": "Direct attack on my heart", "julibrij": "georgeus", "chakanwala": "Very nice \ud83d\udc4d \ud83d\udc4c", "bhaskaraman15": "Woooooooooooooo tapsee ma'am what a humble style", "mohd_hakeem7": "\ud83d\udd25\ud83d\udd25\ud83d\udd25\ud83d\udd25\ud83d\udd25", "hiten_davawala": "\u2764\ufe0f\u2764\ufe0f true", "ravichauhan2233": "Great actor ho AAP", "vikaskumarvikaskumar896": "Super mam", "is_parmar": "Alluring n Spectacular pose", "amayaverma04": "Swagger", "milinddevde": "Tumhari smail keliye tum meri fevret hiroin ho yar. Very nice yar", "khuram.hameed2016": "I like u", "soyebmirza_18": "\ud83d\ude0d\ud83d\udc93", "anilpatel4402": "Very nice \ud83d\ude0d\ud83d\ude0d\ud83d\ude0d\ud83d\ude0d", "vinuvinaycreations": "Right @taapsee", "hima3335": "Randi saali\ud83d\udd25\ud83d\udd25", "ziyamalik17": "Fabulous \ud83d\udd25\ud83d\ude0d", "mukesh_rana90": "Beautiful\ud83d\udc8b\ud83d\udc8b\ud83d\udc8b", "aamitthakur.dhn": "\ud83d\ude19", "akinsin09": "#Taapsee \ud83d\udc93", "uttamsugan": "Love you", "srj_waytohell": "Beaaaauuutifullll\ud83d\udc96", "diksha.aggarwal.121772": "\ud83d\udc4c\ud83d\udc4c\ud83d\udc4c\ud83d\udc4c\ud83d\udc4c", "mr.shourovroy": "that's a cute one..\u2764\ufe0f\u2764\ufe0f", "raviteja7384": "Super", "xhxpc": "Biggest anti hindu actress ever........ and agent if Dawood ibrahim @taapsee", "gauravbhateja2": "\u2764\ufe0f\u2764\ufe0f\u2764\ufe0f", "kuldeep_rohndiya": "\u2764\ufe0f", "sasmitapani_995": "Hey guys dm me", "gpsrathod": "Janeman", "ka_vi_in_": "\ud83d\udc95\ud83d\udc95\ud83d\udc95\ud83d\udc95lovely", "muhammed_isa123": "Gorgeous", "kajal_fan_girl": "\ud83d\udc9c\ud83d\udc9a\ud83e\udd29\ud83d\udc99\ud83d\udc99\ud83d\udc96\ud83d\udc99\ud83d\ude18\ud83d\udc99\ud83e\udd29\ud83d\udc99\ud83d\udc99\ud83d\udc96\ud83d\udc96\ud83d\udc9a", "piyush_dancer1416": "I love you\ud83d\ude18\ud83d\ude18", "sb_sana_bagalkot": "\ud83d\udd25", "kapilkumarg19": "Nice", "arbab_bilal_khan": "Awesome", "birendrakr.sinha": "\ud83d\udc4c", "sarikakhatun456": "\ud83d\ude0d\ud83d\ude0d\ud83d\ude0d", "justdanishzain": "Super", "mukund.ms_08": "Osm.....\ud83d\ude0d\ud83d\ude0d", "rahul9kb": "Love u mama", "davinder3": "Murr Murr k na dekh Murr Murr k \ud83d\ude0a\ud83d\ude0a@taapsee mam \ud83d\udc4c\ud83d\udc4c", "bubbles_crushers": "Nice", "sunita.sehgal": "\ud83d\udcaf", "tanuj9951": "\ud83d\udc8b\ud83d\udc8b\ud83d\udc8b\u2764\ufe0f", "vijay.shankar.50702": "Looking so awesome", "mawj_khan": "\ud83d\udc95\ud83d\udc95", "besyihere": "\ud83d\udc4c", "_rohan__kohli": "Prettiest smile \u2764\ufe0f\u2764\ufe0f\u2764\ufe0f", "saurabhmaddeshiya": "U look always pretty\u2764\ufe0f", "official.sonu.yaduvanshi": "\ud83d\ude0d\ud83d\ude0d\ud83d\ude0d\ud83d\ude0d\ud83d\ude0d", "abrar_singer": "Wow\ud83d\ude02\ud83d\ude02\ud83d\ude02\ud83d\ude02", "harshalbait261": "\u2764\ufe0f\u2764\ufe0f\u2764\ufe0f\u2764\ufe0f\u2764\ufe0f\u2764\ufe0f\u2764\ufe0f\u2764\ufe0f\u2764\ufe0f\u2764\ufe0f\u2764\ufe0f\u2764\ufe0f", "chahatpvt.xx12": "Lovely", "khanna3010": "\ud83d\udcaf\ud83d\udcafsuper mam", "ansari__shama": "So pretty\u2764\ufe0f\ud83d\udd25", "fahadchowdhury7": "\ud83d\udc98\u2764\ufe0f\ud83d\udc95\u2764\ufe0f\ud83d\udc95\ud83d\udd25\u2764\ufe0f\ud83d\udc98\ud83d\udd25\ud83c\udf39\ud83d\udd25\ud83c\udf39\ud83d\udc9e\u2764\ufe0f\u2764\ufe0f", "vicky_5519": "Att", "shishirgusain": "Fabulous...", "sky_aakash_pandey": "U r looking class-apart\u2764\ufe0f", "anamika_dhara_1": "\ud83d\udca3\ud83d\udca5\ud83d\udd25\u2764\ufe0f\ud83d\udc98", "urban.pahadi": "\ud83d\ude0duff\ud83d\ude0d", "prakharverma__": "Love u mummy... \u2764\ufe0f\u2764\ufe0f", "anurag.arora9277": "\ud83d\ude18\ud83d\ude18", "vishal.taneja.351": "\ud83d\udc9d\ud83d\udc9d", "maleek_x": "Love u", "rajnishanand7": "Gajab\u2764\ufe0f", "akanksha_tripathi18": "\ud83d\udc95\ud83d\udc95\ud83d\udc95", "amanv706": "@taapsee Kyyaa .. baaat haaaiii... \ud83d\ude0d\ud83d\ude0d\ud83d\ude0d\ud83d\ude0d", "dreamer__2702": "Gorgeous\ud83d\udd25\ud83d\udd25\ud83d\udc97", "dabhimanishkoli": "Love you sweet heart \u2764\ufe0f\u2764\ufe0f", "neha_thecute": "\ud83d\udc4c\ud83d\udc4c\ud83d\udc4c\ud83d\udc4c", "_chhole_bhature": "I can keep staring \u2764\ufe0f", "anmoloriginal": "Happy belated b'day @taapsee twnu bhot bhot sari well wishes te khainch le qashh de liye v", "itspundir": "\u2764\ufe0f\u2764\ufe0f\u2764\ufe0f\u2764\ufe0f\u2764\ufe0f\u2764\ufe0f", "kumar_utkarsh_singh": "\ud83d\ude18\ud83d\ude0d\ud83d\udc4c", "birju_shinde": "Cute and sweet \ud83d\ude0d\ud83d\ude18", "vikeshkumar1515": "Adroble\ud83d\udd25\ud83d\udd25\ud83d\udd25\ud83d\udd25\ud83d\udd25\ud83d\udd25\ud83d\udd25\ud83d\udd25\ud83d\udd25\ud83d\udd25", "smartsamad143": "U look gorgeous in any pic \ud83d\udd25\ud83d\udd25\ud83d\udd25\ud83d\udd25U R great acting scenes r given God\ud83d\udc4f\ud83d\udc4f\ud83d\udc4f\ud83d\udc4fmadam", "i_am__gopal": "AWESOME AWESOME\ud83d\udd25\ud83d\udd25\ud83d\udd25\ud83d\ude0d\ud83d\ude0d", "ulfawidyaaa": "Aaah you look so beautiful\u2764\ufe0f", "pawan_vaishnav_10": "Osm \ud83d\ude0d\ud83d\ude0d\ud83d\ude0d", "juned_ahmed_saju": "\u2764\ufe0f\u2764\ufe0f\u2764\ufe0f\u2764\ufe0f", "007ashu_tosh": "\ud83d\udc4c\ud83d\udc4c\ud83d\udc4c", "vdharasna": "\ud83d\ude0d", "abulkhyear": "So Beautiful \ud83d\ude4c\ud83d\ude4c\ud83d\ude4c\ud83d\ude4c\ud83d\ude4c", "watch.world10": "VISIT OUR PAGE FOR BEST QUALITY WATCHES AT REASONABLE PRICE", "rebi_99_": "\ud83d\ude0d\ud83d\ude0d", "datta.kamble.73157": "\ud83d\udc90Super\ud83d\udc90", "iamadilkhan95": "Nice, smart !", "praveenrai42015": "Aisa taaap", "mehreen6825": "\ud83d\ude0d", "shabazsuperstar": "Beautiful", "iam_p_c": "This should be your profile pic", "mishra_satya_": "Wawww", "mayur.p.chauhan": "\u2764\ufe0f\ud83d\ude0d\u2764\ufe0f\ud83d\ude0d", "jasmine.suting.3": "U always cute \u263a", "nikkichd": "Looking stunning \ud83d\ude18", "dattashewne": "My crush", "ahmedqureashi": "I love her @ahsanrohan \ud83d\ude02", "tuku748": "\ud83d\ude0d\ud83d\ude0d\ud83d\ude0d", "dr.neha5": "My fav \ud83d\ude18\ud83d\ude18\u2764\ufe0f\u2764\ufe0f", "vickyvicky7328": "\ud83d\ude0d\ud83d\ude0d\ud83d\ude0d\ud83d\udc8b\ud83d\udc8b\ud83d\udc8b\ud83d\udc96\ud83d\udc96\ud83d\udc96", "mathias.boe\nVerified": "Verified", "hemantbhutta": "Sweet", "dhananjaywhatisthisbehaviour": "@muskkk_14 \ud83d\ude02 no difference\ud83d\ude02", "amilokesh": "\u2764\ufe0f\u2764\ufe0f\u2764\ufe0f\u2764\ufe0f", "brijeshyadav7": "\ud83d\ude0d", "2ez4.jatin": "U r amazing\u2764\ufe0f\u2764\ufe0f\u2764\ufe0f\ud83d\udd25\ud83d\udd25\ud83d\udd25", "kumakaushik": "Hi miss beautiful", "arjitm24": "Cute girl", "konhajheidd": "\ud83d\udc4f", "i_aman_verma": "Naina di laser vajdi seedha dil te jaake ni \ud83d\udc95", "devsimranstudios": "eh mutyaar bohot sohni a\ud83d\ude4c", "jolly_dhaliwal_": "Saxy pori aa too", "manish_lakra46": "\ud83d\ude4f", "bhinder_deol": "\ud83d\ude0d\ud83d\ude0d\ud83d\udd25", "bhakti_patel890": "Follow me", "shrikantshah9959": "Kya bat hai", "bhagwat.jadhao.315": "Most beautiful and sweet", "the_deepak_nanda": "\u2764\ufe0f\u2764\ufe0f\u2764\ufe0f", "vinay.rajput.1983": "You are real Queen of Bollywood.", "rk3153871": "Mast taapsee Ji lgy rho pichey mud ke mat dekhna aagy bedty rho", "nabamanatechi": "Oh, Beautiful yaar", "c_a_l_m_to_be_l_e_a_d_00": "\ud83d\ude0d\ud83d\ude0d\ud83d\ude0d\ud83d\ude0d\ud83d\ude0d\ud83d\ude0d", "aatsei": "Charming as always \u2764\ufe0f", "payalpadam": "\ud83d\udd25\ud83d\udd25\ud83d\udd25\ud83d\udd25\ud83d\udd25\ud83d\ude0d\ud83d\ude0d\ud83d\ude0d", "farhana_rahman_heera": "\ud83d\udd25\ud83d\udd25\ud83d\udd25", "beingmickeeyy": "beauty beyond words\u2764\ufe0f", "shishir349": "wowwee wow what a smile", "bhansaliteena": "Sohni\u2764\ufe0f", "abdulkaleem0007": "\ud83d\ude18\ud83d\udc8b\ud83d\ude19", "f.reakygirl": "\ud83d\ude0d\ud83d\ude0d", "soli3151": "\ud83c\udf39AMAZING \ud83c\udf39", "sonalidas387": "Awesome.... \ud83d\ude0d\ud83d\ude0d\ud83d\ude0d\u2665\ufe0f\u2665\ufe0f\u2665\ufe0f", "_incorrect_master_": "\ud83d\ude0d\ud83d\ude0d\ud83d\ude0d\ud83d\ude0d\ud83d\ude0d\ud83d\ude0d\ud83d\udc95\ud83d\udc95\ud83d\udc95\ud83d\ude18\ud83d\ude18\ud83d\udd25\ud83d\udd25\ud83d\udd25\ud83d\ude0d\ud83d\ude0d\ud83e\udd29\ud83d\udca6\ud83d\udca6\ud83d\udca6\ud83d\udca3\ud83d\udca3", "yuktaa.812": "\ud83d\ude0d\ud83d\ude0d", "akashraj0314": "Looking kool \ud83d\ude0d\ud83d\ude0d\ud83d\ude0d", "nupurbhatnagar22": "\u2764\ufe0flove you loads..\u2764\ufe0f\u2764\ufe0f\ud83d\ude0b", "shuktiflora": "Maam recognize me we met at mpgs meerut", "pavankoyyana": "\u2764\ufe0f\u2764\ufe0f\u2764\ufe0f\u2764\ufe0f\u2764\ufe0f", "aryankalra_avneet": "\u0916\u0942\u092c\u0938\u0942\u0930\u0924", "misssakrouna": "\ud83c\udf39", "bhishak76": "fabulous.. U r dream girl", "meheraj.farayezi": "My Heart\ud83d\udc94", "ankur09gupta18": "I like that \ud83d\udc42 earrings ...", "prii__iii": "Cutooooo\u2764\ufe0f\ud83d\ude18\ud83e\udd40", "m_r___d_a_s_h_u": "Nice \ud83d\udc4c\ud83d\udc4c", "smile_king_bro": "Love you api \ud83d\ude18\ud83d\ude18\ud83d\ude18\ud83d\ude18", "amanpatil2001102": "Wooooooooow \ud83d\udd25\ud83d\udd25\ud83d\udd25\ud83d\udd25", "love_problam_sovle": "#Astrologer #Sonu_Pandit \ud83d\udc9009001015890 #all_problem_solution #vashikaran #get_your_love_back #black_magic_specialist #love_marriage_specialist (#\u092b\u0940\u0938_\u0915\u093e\u092e_\u0939\u094b\u0928\u0947_\u0915\u0947_\u092c\u093e\u0926)\u092a\u0924\u093f \u092a\u0924\u094d\u0928\u0940 \u0905\u0928\u092c\u0928 \u0938\u094c\u0924\u0928 \u0926\u0941\u0938\u094d\u092e\u0928 \u091b\u0941\u091f\u0915\u093e\u0930\u093e \u0938\u0941\u0916 \u0936\u093e\u0902\u0924\u093f \u0918\u0930 \u0915\u094d\u0932\u0947\u0936 \u091c\u0948\u0938\u0940 \u0938\u092e\u0938\u094d\u092f\u093e \u0915\u093e \u0938\u092e\u093e\u0927\u093e\u0928 \u0918\u0930 \u092c\u0947\u0922\u0947 call new WhatsApp 09001015890", "jnmhv": "\u2665\ufe0f\u2764\ufe0f", "yashbhardwaj796": "\ud83d\ude0d\ud83d\udd25", "roshanshettyrg": "\u2764\ufe0fgood....pic", "the_akash_kumar_12": "\u2764\ufe0f\u2764\ufe0f\u2764\ufe0f\u2764\ufe0f\u2764\ufe0f\u2764\ufe0f\u2764\ufe0f\u2764\ufe0f", "p.v.ram": "\ud83d\ude0d", "p.karunadevi": "\u2764\ufe0f", "subhamrambo": "Beautiful", "r_c39": "Amazing looking\ud83d\udc4c\ud83d\udc4c\ud83d\udc4c\ud83d\udc4clove you", "stutipriyadarshani": "Looking beautiful\ud83d\ude0d\ud83d\ude0d", "nikhilmalik55": "\ud83d\udca5\ud83d\udca5", "uxair.uz99": "\ud83d\ude0d\ud83d\ude0d\ud83d\ude0d", "ganeshshastriasr": "Ek phone mein Chamatkar Pau Pandit Ganesh Shastri 72 ghante Mein all problem ka solution vashikaran love marriage Karobar Kiya karaya Sotan Dushman chutkara ek phone mein Chamatkar pao.9888157646", "varun_taapsee_sathi": "Looking so cute \ud83d\ude0d\ud83d\ude0d\ud83d\ude0d\ud83d\ude0d", "mayurmahajan1987": "\ud83d\ude0d\ud83d\ude0d", "mahtab_09a": "\ud83d\udd25\ud83d\udd25\ud83d\udd25\ud83d\udd25", "kailashkmrr": "\ud83c\udf39\ud83d\ude48", "mr.kh6n": "Beautiful", "milind844372": "\ud83d\udd25", "debolinaaa__2902": "\ud83d\udc9c\ud83d\udc9c\ud83d\udc9c\ud83d\udc9c", "sweetweapon_96": "Wowwww \ud83d\udc95", "vidya358": "\u2764\ufe0f\u2764\ufe0f", "jabber2d": "\ud83d\ude02\ud83d\ude02\ud83d\ude02", "iamacn": "The real Fashionista\u2764\ufe0f\u2764\ufe0f\ud83d\udd25\ud83d\udd25\ud83d\udd25", "shrutiiii__sharma": "Pretty \ud83d\udc95\ud83d\udc95\ud83d\udc95\ud83d\udd25\ud83d\udd25\ud83d\udd25", "sonamjackie": "Beautiful.", "____mr.avi____": "\ud83d\ude0d\ud83d\ude0d\ud83d\ude0d", "the_hippie_sleeve": "Dreammmm \ud83d\ude4c\ud83d\ude0d", "indi.an224": "\ud83d\ude2e", "slaywithstylee": "Pretty\ud83c\udf38\ud83c\udf38", "rapha_johnson_": "\ud83d\udc9c", "kviitmmeme": "sexy!", "_sparsh_sharmaa_": "\ud83d\udd25\ud83d\udd25\ud83d\udd25\ud83d\udd25", "rram2306": "\ud83d\ude0d", "reshmi_rumi91": "looking faaabbbbbb @taapsee di...\ud83e\udd17\ud83c\udf39\ud83d\udc96", "sumukhrai47_boxer": "\ud83d\udd25\ud83d\udd25\ud83d\udd25", "nick_narkar": "Wow your so beautiful \u2764\ufe0f", "neerjais22": "So pretty", "bmal2019": "\u2764\ufe0f\u2764\ufe0f", "tanviwadhar": "Youu\ud83d\ude0d", "taskin.sultana.123": "\u2764\ufe0f\u2764\ufe0fxectly...hehe\ud83d\ude02", "im_ruhgupta8585": "nice", "ava_dips": "Muaaaah!!!!\ud83d\ude23\ud83d\ude18", "sairabanosk": "\u2764\ufe0f\u2764\ufe0f\u2764\ufe0f\u2764\ufe0f", "lollylit": "Emotionally leaking!! \ud83d\ude05\ud83d\ude48", "dadhwal1322": "\u2665\ufe0f", "_jai_jr_": "Any new movies", "afsarshaikh24": "so superb", "gigidogaru0": "Numar", "iambobcristo": "Beautiful", "mithunkr79": "Hot and sexy", "prasen_bharshankar": "\ud83d\udc4c", "therahulsharmag": "\u0924\u0947\u0930\u093e \u0905\u0902\u0926\u093e\u095b-\u090f-\u0938\u0901\u0935\u0930\u0928\u093e \u092d\u0940 \u0915\u094d\u092f\u093e \u0915\u092e\u093e\u0932 \u0939\u0948, \u0924\u0941\u091d\u0947 \u0926\u0947\u0916\u0942\u0902 \u0924\u094b \u0926\u093f\u0932 \u0927\u0921\u093c\u0915\u0947 \u0928\u093e \u0926\u0947\u0916\u0942\u0902 \u092c\u0947\u091a\u0948\u0928 \u0930\u0939\u0942\u0901\u0964", "raina_ghosh": "Pretty \ud83d\udc4c\ud83d\ude0d\ud83d\ude0d\ud83d\ude18\ud83d\ude18", "sunil_kumar08": "\u2665\ufe0f\u2665\ufe0f\u2665\ufe0f\u2665\ufe0f", "retnoyudharma6": "Wearing Batik clothes...i love it...", "aakankshag1": "\ud83d\ude0d", "____mhsn____": "Ooo jigr @hamed.sinaa \ud83d\ude02", "pritam.bafna_": "@taapsee So Cute !", "jyotsna_jonas": "\ud83d\ude0d\ud83d\udc95\ud83d\udc95\ud83d\udc95", "neha.a80": "\ud83d\ude0d\ud83d\ude0d", "hayath.123": "\u2764\ufe0f", "director_pradeep_pokhriyal": "I love you\ud83d\udc93", "k.bachhal": "\ud83d\udc4c", "afreenafu": "Dreamyyyyyy\u2764\ufe0f", "gundusonaraha": "So lovely smile", "_theartsy_lens_": "@rana_bhaaiii @rana_bhaaiii @rana_bhaaiii", "manasi_ghadigaonkar": "I'm falling in love \ud83d\ude0d\u2764\ufe0f", "ritesh_k_ail": "Mast lovely beautiful", "taapsee__": "\ud83d\ude0d", "arpit22agrawal": "Ak chand...dusri aap..", "sukhdeep2991": "Nice"}