{"reneethereborn": "Wow so beautiful girl \ud83d\ude0d\ud83d\ude0d", "mybirdjacket": "Loving this super comfy outfit ..you are beautiful \ud83d\udc9c", "vasudhadada": "Very beautiful \u2764\ufe0f", "jugniandco_": "Pretty chhokri \ud83d\udca5\ud83d\udc96", "thestylechefs": "Such a lovely caption ! \u2764\ufe0f", "fashionstylebyjohanna": "\ud83c\udf80Klasse \ud83c\udf80", "dishyyyyyyyyy": "May your future be as bright and vibrant as this outfit! Beautiful! \ud83d\udc9f\u2728", "suitsandglutes": "Man oh man I need to find me some good walls \ud83d\ude0b", "cloudy_thoughts9": "Omg the colours are beautiful and ur hair are on fleek! @shes_a_sixteen \u2764\u2764\ud83d\udc8e\ud83d\ude18", "theflawlessfactory": "I love that shade of yellow\u2764\ufe0f\u2764\ufe0f", "sagarikapatil": "Wow amazing \ud83d\udc97\ud83d\ude0d", "kautuka": "This was a good shoot day! \ud83d\ude42", "stylemearia": "Gorgeous picture \ud83d\udc96\ud83d\udc9b", "lovelifefashionstyle\nVerified": "Verified", "nidhikashah14": "Beautiful colours", "thestylechair": "Love the bright shades\ud83d\ude0d", "alexie.co": "Gorgeous", "thetinkersoul": "The colors look gorgeous on you \u2764", "stylewithpriyanka": "Love the way you've put all together \ud83d\udc93", "shishta_vineyardpassage": "Colors are so pretty..", "onegirlherjourney": "You always look pretty!", "tres.envogue": "Such lovely bright colours \ud83d\ude0d", "noopurkalra": "Love the colour blocking \u2764", "priyanka_nahata": "@jyotii_jain @monika.20", "shes_a_sixteen": "#ShesASixteen #pune #puneblogger #punegirls #punefashionblogger #puneinstagrammers #munbaiblogger #mumbaibloggers #lotd #wiwt #liketoknowit #style #fashion #colours #plussizefashion #curves #maxi #friday #streetstyle #love", "nehasharma07": "This is very beautiful lengha", "priyankasrana": "Beautiful outfit beautiful you \ud83d\udc95\ud83d\udc9b"}