{"srisht1": "@vrinda013 oh", "_chanduuu_": "@mallika____ and I'll buy you this one", "ishimasalapisi": "@_ruchika_sometimes_ pehen le", "aishtacy": "@isinjini", "dollmarana": "@suri.shilpi laa do Didi yeah", "suri.shilpi": "Apt hai apke liye toh", "shr.j23": "wish I could give you this on your birthday @yashrajaishwarya", "yashrajaishwarya": "\ud83d\ude12\ud83d\ude12@vartikahere", "navigator.chauhan": "Sexy\ud83d\ude18", "the_wanderer_india": "@azzy.doon \ud83e\udd23\ud83e\udd23\ud83e\udd23\ud83d\udd25", "siirjann": "@ayushii24 you.", "mrsholmes221b": "@noturgurll_ imma gift this to you", "sinderellla._": "@adhya.pandey remember you were asking me what do I want for my birthday?\ud83d\ude0c Well...\ud83d\ude0c", "shivani.patel98": "@reshamchandwani for you\u2764\ufe0f", "anshven": "@zeshanchowdhary kutti", "sharmishta_roy": "@sunnydwivedi kharid le \ud83d\ude1c", "perksofbeingalya": "@ahdia2702 love this one", "vaishnavi__7755": "@changing_haripriya I think .....this will be perfect gift \ud83d\ude02\ud83d\ude48\ud83d\ude48", "megha.hazarika_": "@tafrin_s perfect gift for you \ud83d\ude02\ud83d\ude02\ud83d\ude4c\ud83c\udffb", "sanaabkhan": "@amani_alyy", "aditiiiily": "This is perfect for @simoni_4255 and @neelamkankani02 you guys\ud83d\ude02", "anushar6x5": "\ud83d\ude02\ud83d\ude18\ud83d\ude18\ud83d\ude18\ud83d\ude18\ud83d\ude18\ud83d\ude02", "26_nov_bhavika": "@thepunjabichick i will gift you this\ud83d\ude02\ud83d\ude02", "ne10ya": "@prazeek", "prazeek": "@ayushi__spam101 lol this on for sure \ud83d\udc81\u200d\u2642\ufe0f\ud83d\udc81\u200d\u2642\ufe0f\ud83d\ude02", "neelthepoet": "Agar ye baat bhale hi koi mazak me keh deta. To ab tak bawal ho jana tha.", "khansadiya_": "@ritikashar we need this \ud83e\udd23", "aashinakaul": "@manikasharma27", "dikshagupta97": "@kanikadhawan27 @yashikaarora17 @tarandeep7868 \ud83d\ude02\ud83d\udc4c\ud83d\udc4c", "juhibhatt": "@surbhisahu", "aj.d.singh": "Me female dog will wear this for sure gonna buy one", "vartika_x": "@kpissij buy me this", "wanderer_panda_": "Mere girlfriend ke liye ek lena hai...\"\u0918\u094b\u095c\u0940\"", "sadmavatii": "@_sunnda_shrma_ yaaarrr ye mangwaenge", "jayanti_kumari111": "@ranjana_tewatia_ I LL buy you this", "cenzenah": "@aayushi_martoliya", "_shikha_lakhe": "@its_shilpo", "salmaanrajput786": "Gorgeous", "lovelaughlive4ever3008": "\ud83d\ude06\ud83d\ude06\ud83d\ude06\ud83d\ude06\ud83d\ude06\ud83d\ude06", "sahiba_chahal21": "WOW\ud83d\ude0d", "the_awkward_traveller": "@phirki", "01ayushisharma": "@01vishalyadav visssshhaal", "kashishsrivastavaa": "@manyaaa01 yeh chahiye meko :) just saying", "simmimatharoo": "@tooofan_ka_devta ye dekho", "prabphull": "Priceeeeeeeee please", "bhav_dhn": "@mallikadua can someone deliver this to Canada as well? Me and bff @malangmerchant wantttt this so badly.", "tereesa_tj": "@_niti._ @_sonal_1821", "avani_ranjan": "\ud83d\ude02", "shreemganguly": "Kyaut", "mansi._j": "@tanishka._j", "aanshi_desai": "@priya9393 @aashnahluwalia I want this", "deeptisac": "@paroparomita yeh \ud83d\udc46\ud83c\udffc", "s.hantan.u": "@jatinjuneja_ you should get this", "deedeshmukh": "@meghadeshmukh17 tumhare liye", "dhana_shri007": "\ud83d\ude02\ud83d\ude02\ud83d\ude02", "kirtib1708": "Hahaha akhir apne naam ka patta pahen hi lia @mallikadua", "innerfoodie101": "I really don't think any person would want to wear a tag around their neck that says '\u0915\u0941\u0924\u094d\u0924\u0940/\u0915\u0941\u0924\u094d\u0924\u093e' stop publicizing just anything.", "samara_sail": "@elishachopraa", "navita_bajaj": "@nanz0207 kutti \ud83e\udd23", "darkest__hour": "Hahahahahaha. \ud83e\udd23\ud83e\udd23", "sugardaddy_333": "aaj apne aap ko pehchan hi gyi!!\ud83e\udd2a\ud83e\udd2a", "hargunsabharwal18": "@shivangi.shekhar want this\ud83d\ude2d\ud83d\ude2d\ud83d\udd25\ud83d\udd25", "iammonikachoudhary": "@choudhary_neelam your birthday gift \ud83d\ude02", "priyaaa______": "That tharki face when you see a hawtt guy! @aanchalllll_ @_niyati_24 @bhoomishah04", "rekhapathak862": "The chain cute", "paklod": "\u06a9\u062a\u06cc\u0627", "manssss.pvt": "@issahirannz goals", "aakanshabadola_": "@mitalijethani We need this\ud83d\ude02\ud83d\ude02", "salonidhumal": "@divyametkar and @viraagidurgaa made for us", "dungardanu": "Nice", "somikkhya": "Where can I get this", "sakshi_gaur25": "@arsheya.mithal @aradhnamahajan I am buying this for us", "agyapragya": "Woww\ud83d\ude02\ud83d\ude02\ud83c\udf38", "aaliya_makeup": "\ud83d\ude0dSo meaningful", "meazmtkhan4": "What is this\ud83d\ude02", "itsmemukku": "Yeh tha\ud83d\ude02\ud83d\ude02 tujhe gift kru?\ud83d\ude1c", "sallume_binmahfouz": "Cutiepie luvly \ud83d\udc9e", "anikabhutani": "@nikhilm1 @kanksha17 gedding it\ud83d\udd25", "mondal.ankita": "This is hilarious #didispecial \ud83d\ude0b\ud83d\ude0b", "dasjustsowow": "@bhatia.niharika i want this!!! Please.", "forever_a_mountain_girl": "@ankita_joshal had to be you \ud83d\ude02\ud83e\udd23", "tanoj__": "Kutti", "nandandutta": "HHaaahhaaa", "romanchitabharadwaj": "Didi\ud83d\ude0d\ud83d\udd25", "keepingupwithkanak": "One for me too pleassssss\ud83d\ude4f\ud83d\ude4f", "pednekarchetna": "Does not suit you...your a sweet lil cutie pie", "deday_a": "\ud83d\ude1d\ud83d\ude1d\ud83d\ude1dU r 2 much\ud83d\ude02\ud83d\ude02", "lambaghinny": "it says kunti...lol", "somyagupta21_": "We're all kuttis. Send us plisssss. Also my best friend. Also my 3 sisters. And also my ex current favourite girl.", "imshreenidhi": "That lip bite \ud83d\ude0d", "bhawna1870": "\ud83d\ude01", "shrutipce": "@snehachimnani yeh le lete hai", "petitestar.me": "@pallavis we need this!", "pri_tin": "\ud83d\ude02\ud83d\ude02 kya baat ...", "tanyaaarora": "@priyaamalhotraa BUDDDYYYYYY", "aqueercat": "@taniamitra1234 @dshrutib @tuba.waqar WANT", "nikita102215": "@dishaa3012 @sonalp91 @__priya95_ im gonna wantz", "kastoo25": "Hadd Ho gyi \ud83d\ude0a\ud83d\udc4f\ud83d\udc4f", "himalya_7797": "Don't tell me you don't have \"kutta\" one?", "vanya_1965": "\ud83d\udc15\ud83e\udd70", "dbartwal25": "\ud83d\ude18\ud83d\ude18\ud83d\ude18", "ibreathtrends": "What does it say guys???", "japjeetd": "@tulikapanwar the next thing we are going to twin in!! \ud83d\ude02\ud83d\ude01", "shramika_sharma": "@vega_shetty @divya_nair_ \ud83d\ude02", "meenaltaru": "@sgfitnessguide @mariya.amreliwala", "yukti_jagtiani": "@mallikadua hopefully u send me one too\ud83d\ude09\ud83d\udcaa\ud83c\udffc", "alyan.ani224": "\ud83d\ude0b\ud83d\udc45", "whimsynerd01": "We need to get it too @sentibenozukum", "shahwaralikhan": "\ud83e\udd23\ud83e\udd23\ud83e\udd23", "vipulkanodia": "Being kutti.", "ahujageetika": "@ahujaaakriti you want this? \ud83d\ude1d", "sarvgun.somepun": "@sargun_arora01", "_kriti_g": "Ohk so as everyone asking, send me too, but along with K for Kamini \ud83d\ude02\ud83d\ude18\u2764 #kuttikamini #loveyou #girllove #badassgirls", "shubhra_5": "\ud83d\ude06", "trisha.raichand": "@tannu1511 \ud83e\udd23", "ochanihimani": "@bhumika.ochani", "surabhi_gaikwad_artist": "@nomadictej \ud83d\ude0a", "archa_mishra": "@sumbul_shamim , @poonamtulshiyan , @shubhy21 \ud83d\ude02\ud83d\ude02", "lovelysona29": "@thisistarunzz", "mitalivakil": "@mallikadua adding colour to our life \ud83d\ude4c", "rajpalcharu": "\ud83d\ude02", "ketkipawar5": "@nikki_luckystar we need ths pendant\ud83d\ude02\ud83d\ude02", "sarikaagnihotri3333": "@nandanniiiiii", "himanshi.chetwani": "@poornima747 LOL LOL", "sanjanahk": "@_reema_g", "mysa_khan": "I loved it..", "viinii_05": "Want want want \ud83d\udc93", "naazishb": "@meghasharma.__ Found your next birthday gift \ud83d\ude42", "iamharleyquin": "@nautankiwaali @thechopranextdoor want?", "gourav.jaiswal": "\u0915\u0941\u0928\u094d\u0924\u0940 .!! \u092a\u093e\u0902\u0921\u0935\u094b\u0902 \u0915\u0940 \u092e\u093e\u0901 \u0915\u0941\u0928\u094d\u0924\u0940 .. ? \ud83d\ude1b", "azul_maniac": "@pournamyshyam ye banana next time dukan me", "megha611": "@shermeens @warriorandthegypsy \ud83d\ude02\ud83d\ude02\ud83d\ude02\ud83d\ude02 matching necklaces again???", "hapeezippyishita": "@guptapragati4 :D", "jaspreet_khippal": "\ud83e\uddc0 if u get it \ud83e\udd23", "tau5818": "Cheap", "smile_sunshine16": "@dev_drishya", "krutikasamant": "You found a perfect gift for me @shruti.bhagwat", "rozalsingh": "@shivali.khurana lol", "mistletoe_0908": "@tanishkachoudhary54 ye le tera bdday gift\ud83d\ude02\ud83d\ude02", "sakshh018": "@anveshamathur @kanishka_khinchi", "sadaffatima1609": "@fat.ima.hum.era i want one \ud83d\ude00\ud83d\ude00", "sumanadang": "LOVE THISSSSSSSSS DUA\ud83d\udd25", "tanushrimishraa": "ye le le tu @iamnavedika Kutti \ud83e\udd70", "xharshitx": "@shreshthahuja forget that, buy this one\ud83d\ude02", "faijanknice": "\ud83d\ude2c\ud83d\ude08Bitch\ud83d\ude08\ud83d\ude2c \ud83e\udd23\ud83e\udd23\ud83e\udd23", "stuff.potato": "@himaniimahajan", "ilhamaboo": "Superrrrerrer\ud83d\udc4f\ud83c\udffd\ud83d\udc4f\ud83c\udffd\ud83d\udc4f\ud83c\udffd\ud83d\udc4f\ud83c\udffd\ud83d\udc4f\ud83c\udffd\ud83d\udc4f\ud83c\udffd\ud83d\udc4f\ud83c\udffd", "nehalchawla_": "@prishatalwar @gazia.parveen15 @_jahanvi_10", "tanushr.ee": "OHMYGODDDDD", "nikita80910": "Jabardasst", "smobin304": "\u0915\u0941\u0902\u0924\u0940...???", "nivliveshere": "@nikitasahota @shachi.nelli round 2", "aayushi.mithi": "@anu_indoria this is so me! \ud83d\ude0d\ud83d\ude09\ud83d\udc95", "disha.f": "Teri Yaad aayi ye pendant Dekh k @nivishastri", "seemarohan": "This us hilariousl", "supriyasonawane": "Disgusting", "rashidsamad": "jangli ya paltu ..... lol", "_mystictrail_": "@priya11july @tannak_", "nisha_bilkhiwal": "@nikita_mathur_1947 \ud83d\ude02", "sabaislamk": "I cant believe i am saying this but i would actually want one..\ud83e\udd26\u200d\u2640\ufe0f\ud83e\udd13", "catch_the_case_": "Awesome!!! Check out our page sale is going on buy any 4D. Name case @270\u20b9 only", "sabatinishashi": "\u2764\ufe0f from Bangladesh dear.. \ud83d\ude18", "snehabagali": "@td_1913", "amey_tik": "Suits your personality", "lovi_pal": "@icanishqa.g get this one for us naa", "rajitdev": "\ud83e\udd23\ud83e\udd23\ud83e\udd23\ud83e\udd23\ud83e\udd23\ud83e\udd23\ud83e\udd23\ud83e\udd23 @mallikadua", "mallikaranawat": "Not at all cool", "the_real_pari": "Dayum! \ud83d\udd25\ud83d\udc4f", "gwenda30": "@gayle.lennox Get me nowwww\ud83d\ude02", "imthebijleebabujiisafraidof": "@shaleenmamgain shopping ideas.", "priya_akansha": "@rakshapriya95 tere liye banwayenge ye locket...!!! \ud83d\ude02", "muskan.who": "Kuti\ud83d\ude02\ud83d\udd25", "_purpleminded_": "Ye chahiye bday gift? @mansilodaya", "iamrheavirmani": "But this for me already @bawabiker", "talk2sarika": "\ud83d\ude02", "ananyas25": "@udits11 lol", "jhalakjain23": "@i_got_no_cool \ud83d\ude02", "yogwithsalonii": "@keshavdhamija1999 \ud83e\udd23", "kazi.rehaab": "@varunnailedit \ud83e\udd23I buy this for you shingatayyyyy", "priyanka_bhatia91": "@aanchalkulchandani YOU HAVE TO GET THIS FOR ME NYHOW", "iam_mickyy": "@shailja_goswami tu khreed le ek", "adi_bubna": "Kaaaaaaatil\ud83d\udda4\ud83d\udda4\ud83d\udda4\ud83d\udda4. Kitna ka ?\ud83d\ude0d", "brarsman_azam9in2by11": "\ud83e\udd13\ud83e\udd13\ud83e\udd13\ud83d\ude03", "covering_the_covers": "Only @mallikadua have the guts to bring out something like this! \ud83d\ude4c", "amrita_world11": "Hahahhahahahhhahahhahahahahaahhahahwh\ud83d\ude02\ud83d\ude02\ud83d\ude02\ud83d\ude02\ud83d\ude02", "dr.ranjit___singh727": "\ud83d\ude02\ud83d\ude02\ud83d\ude02\ud83d\ude02\ud83d\ude02\ud83d\ude02\ud83d\ude02\ud83d\ude02\ud83d\ude02\ud83d\ude02\ud83d\ude02\ud83d\ude02\ud83d\ude02\ud83d\ude02\ud83d\ude02\ud83d\ude02\ud83d\ude02\ud83d\ude02\ud83d\ude02", "_._.pragatii._._": "This is so \ud83d\udd25\ud83d\udd25", "debjanicaroleaich": "Need.", "tanception": "yassseee omg.\ud83d\udd25", "solicitoussoul9": "\ud83e\udd23\ud83e\udd23\ud83d\udc4c\ud83c\udffb\ud83d\udc4c\ud83c\udffb", "harmanbajwagarg": "Who's are saying I want one I want one. Inko real life mein koi kutti bol kr to dikhaye lol kya dramebaazi \ud83e\udd23\ud83e\udd23\ud83e\udd23\ud83e\udd23\ud83e\udd23 what kind of women empowerment is this?", "sakshampremi": "@tejaswinixx gimme gimme", "nishjain94": "@aditisood1 this is what you getting for your Birthday '19", "komalmadhok": "@9neha @kanika.malhotra136 @nikita21bisht \ud83d\ude1b", "sam.spinz": "\ud83e\udd23", "lokonathpanda": "Thik likha he", "er.mosoof": "kutti\ud83d\ude02\ud83d\ude02\ud83d\ude02\ud83d\ude02\ud83d\ude02\ud83d\ude02\ud83d\ude02", "realmohitjain": "@yodisha777", "harleenkaur_0009": "\ud83d\ude3bWant", "kaj8425": "@atuldhiman326 dilade\ud83d\ude02", "amyradastur93\nVerified": "Verified", "sowmya_ramanathan": "@arushee_srivastava \ud83d\ude02", "bhagyashree_d_gade": "Right!!!!!\ud83d\ude18\ud83d\ude18\ud83d\ude18\ud83d\ude18\ud83d\ude18\ud83d\ude18\ud83d\ude18\ud83d\ude18\ud83d\ude18\ud83d\ude18\ud83d\ude18\ud83d\ude18\ud83d\ude18\ud83d\ude18\ud83d\ude18\ud83d\ude18\ud83d\ude18\ud83d\ude18\ud83d\ude18\ud83d\ude18\ud83d\ude18\ud83d\ude18\ud83d\ude18", "shreyadhamaal": "@pranjalikamal me", "amanscuf011": "\ud83d\ude02\ud83d\ude02kutti", "rumnamukherjee": "\u2764\ufe0f\u2764\ufe0f wow \u2764\ufe0f\u2764\ufe0f", "mannietripathi": "@saharkayani", "crimsonvial": "@guru_k_kaur \ud83d\ude0d\ud83d\ude02", "priyas1703": "\ud83e\udd23\ud83e\udd23\ud83e\udd23\ud83e\udd23 @pooja_1027", "namaste_stalker": "\ud83d\udd25\ud83d\udd25hottest @gaayu_24", "mano_rajkumar": "\ud83e\udd23\ud83e\udd23\ud83e\udd23", "iamkirankk": "He I already ordered something form Pipabell m dam excited for it....", "_saranya_7": "@_ri_.ri I . Want.tjis", "praveen_rana_01": "Beautiful....kutti", "muskan.thukral": "Omg\ud83d\udc9b", "iamtaranarora": "Tere liye le lu\ud83d\ude02 @may_b_a_dreamer", "kunsahuja": "@queenofsaigon23 I know you\u2019re lowkey digging", "like_a_look_": "Cutest", "shokhu_": "Lovely\u2665\ufe0f", "huesofdarkanddeep": "Want!!!!!!!", "awesamosa": "Will buy for us. @nistapistaa", "parorani": "Hahahahahahahahahahahahahahahahahaha", "sneha_venu": "@ruhinishath .. I'll get you this one \ud83e\udd23", "shraddha.sankaye": "@mohini.sangvikar15 tuzyasathi\ud83d\ude02", "life_keep_it_simple": "\ud83e\udd23\ud83e\udd23\ud83e\udd23", "chic_a_pose": "Whaaatttttt\ud83d\ude31 can\u2019t wait didi\u2764\ufe0f", "dishantkumawatd": "True \u263a\u263a\u263a\u263a", "utsabhatia": "ALSO RESLLY NEED THIS @faizasmk", "bhumika_sharma_": "\ud83d\udd25\ud83d\udd25\ud83d\udd25", "vj_prmr": "It's ur real name ?? \ud83d\ude01", "khushboo_pratik": "@sneh.vashi @dhrutinaik7", "arjunmadan": "@ambikavohra i will gift this to you for sure", "priya_negi23456": "that lip bite didi\ud83d\ude06\ud83d\ude4c", "shadesofmoon": "Scyaaaaaauzzzzzz cute pendant alert \ud83d\udc9a\ud83d\udea8", "aestheticallyghettobaby": "Scyauz me, they're the best", "riya_shrivastava__": "@wolfieeesin", "_megha95": "@h_barsha", "_heeeeena_": "Omg OMG omg!!!!!", "eshxkaaaaa": "I love this.", "swatcat86": "The Jewellery I need to buy you is Comjng Soon! @khannakhazana \ud83d\ude02\ud83e\udd18\ud83c\udffb\ud83d\ude0e\u2764\ufe0f", "purvisinha10": "Littt\ud83d\udd25\ud83d\udd25\ud83d\udd25\ud83d\udd25\ud83d\udd25", "yogeetarane": "Hahahha that's my favourite word for my besties \ud83d\ude0d @mallikadua u rock", "bearilucious": "\ud83e\udd23\ud83e\udd23\ud83e\udd23\ud83e\udd23 too good , meinu BHI chahida !!!! \ud83d\ude0d\ud83d\ude0d", "parul_chourasia": "\ud83d\ude00\ud83e\udd18", "aayushijariwal": "@gargi_priyamwada we found a perfect gift for each other .", "__keepingitsimple____": "\u2764\ufe0f\u2764\ufe0f", "_.richa.31._": "@radhikaagarwal12 bro exclusively for you\ud83d\ude01\ud83d\ude02", "zeishahamlani": "Omgggggggg \ud83d\udd25\ud83d\udd25\ud83d\udd25\ud83d\udd25\ud83d\udd25\ud83d\udd25\ud83d\udd25", "jazz_mukherjee92": "Hahahaha", "mehtaashley": "@anoushkabali let's get this necklace \ud83c\udf1a\ud83c\udf1a", "aparnashandle": "\ud83d\ude0d", "sassymomworld": "Hahahahaahja", "gisellejose25": "@shuhneees NEEDDDD\ud83d\ude2d\ud83d\udd25", "anxioussssxx": "@discodiwani yr we have to buy this!!\ud83d\udc98", "dhvaniparikh": "@minalchoudhary19 ur shaadi gift.. Aisa same necklace", "puppypanda": "NEED", "mehersachar": "KWEEEN", "vineeta_laskar": "@rupalit", "vicky08___": "Ye mast hai.. i will buy this for you @as_per_casper", "_praspeed_": "Best \ud83d\ude0d\ud83d\udc99\u2744\ufe0f\ud83d\udc99", "sona_akbani": "It's kyut \ud83d\ude00 dedezzzzzz but thode saste hooon to khareedne main maza ayga \ud83d\ude02\ud83d\ude02\ud83d\ude02\ud83d\ude02", "richas1092": "Haha . This is epic ..", "riley_khan01": "@nehakhan410 @mini_thakur14 \ud83d\ude02\ud83d\ude02\ud83d\ude02", "sassy_sat24": "Ek number! \ud83d\udc96", "amzyamzu": "Nailed it \ud83d\ude02", "dimple.saxena": "Please order two for me\ud83d\ude48\ud83d\ude02\ud83d\ude02", "poojavashistha5": "Awesome \ud83d\udc4f", "aditya_kapoor_7": "@mallikadua cleavage \ud83d\ude0d", "forever_yoursssssssssssssss": "Wow you have Guts \ud83d\udc4f", "getoffyourphonevidhi": "The most apt birthday gift for you. @iamteejeh \ud83e\udd23\ud83d\udda4", "nehasahani": "@sahanidhi I feel bad for people who cannot read Hindi \ud83e\udd23\ud83e\udd23\ud83e\udd23", "thatsakhtlaundaa": "\ud83d\ude2d\ud83d\ude0d", "rosydahiya": "@dr.varshadabas", "exploringpakwaan": "\ud83d\ude0d\ud83d\ude0d\ud83d\ude0d", "hinabi": "wattawow!!", "aainadutta": "Need \"whatawow\" as well.", "dsouzaanisha": "@priyankasikarwar_92", "samruddhi.97": "@shrawasti_13", "sim.ash": "@pupsy209 \ud83d\ude02", "arpita_katyal": "@tkboss_96 dude want", "bhoomika_anandani": "\ud83e\udd23\ud83e\udd23\ud83e\udd23\ud83e\udd23 The pendent tho \ud83e\udd23\ud83e\udd23", "poonam50": "Gal wich ke paya. Ayy", "pravsaran": "@heysiri2510 get yourself this too\ud83d\udd25\ud83d\ude02", "shaikhankita": "Lol", "_mishhhhh_": "@sravani_97 see this bro", "hridikkaa15": "\u2764\ufe0f\ud83d\ude0d\ud83d\ude0d\ud83d\ude0d\ud83d\ude0d\ud83d\ude0d\ud83d\ude0d\ud83d\ude0d", "nomadicwardrobe": "Didi Wahhh", "sameekshakhanna": "@therealshinchaan your birthday gift will be this from my side \ud83d\udd25", "harpreet_singh_kataria": "\ud83d\ude02\ud83d\ude02\ud83d\ude0d\ud83d\ude0d\ud83d\udc4c\ud83d\udc4c", "somyaajoshi": "Dyingggg\u2764\ufe0f", "thenaiveguy": "Oh lawrd i need this..\ud83d\ude02\ud83d\udd25", "tarunsingh.tilwar": "\ud83d\ude02", "6nidds9": "Didi\u2764\ufe0f", "janvi_.rai": "Cool", "miss_kuku1": "Waiting", "yuktialagh": "I want this", "nainabora_": "@tanishkaranga @nandini_pradhan I\u2019ll gift this to y\u2019all", "rukkubhatia_": "Wowee", "shoulda.woulda.prada": "Want want", "kayyyyemm": "@clumpsyperson @voodoomamajuju._ we're getting this", "its_smariiee": "@sweet_susovita @its_suvangi girls we need this na\ud83d\ude2d\ud83d\ude0d\ud83d\ude2d\ud83d\ude0d", "arushi_kharbanda": "@sneha._._.singh", "tjshirin": "Gazab kar diya! \ud83d\udc4d", "urja_jagrut": "@ishamaheshwari_ we need to get this for obvious reasons", "khyatirajput": "Sweetest soul\u2665\ufe0f who is always crystal clear\ud83e\udd17", "pdhaque": "\ud83d\ude02 \ud83d\ude02 \ud83d\ude02", "gurdipgangar": "This is not didi type status \ud83d\ude02", "parihita": "\ud83d\ude0d\ud83d\ude0d\ud83d\ude0d Hey guys!! Checkout and follow @parihita for amazing clothing collection \ud83d\udecd\ud83d\ude0a", "not_girlygirl": "Diddddiii !! Kitnaaa cool !! \ud83d\ude2c\ud83d\ude48\ud83d\ude48\u2764\ufe0f\u2764\ufe0f\u2764\ufe0f", "deekshamehta13": "I\u2019m so buying this \ud83d\ude0d\ud83d\ude0d", "abhinavv30": "\ud83d\udd25\ud83d\udd25\ud83d\udd25", "rahuljain1204": "Kutti ??\ud83d\ude2c\ud83d\ude2c\ud83d\ude2c @mallikadua", "artistic_diary___": "\u2764\ufe0f", "sharma_kumud_": "Diddi itz so bitchy", "tanushiyakeem": "Hahahahahahaha need this", "gauravchhabra2212": "Who else has these guts.....", "pallavisrivastava93": "Waaaaaaannnnnnnnt", "manali_korde": "@grishmakorde \ud83d\ude02", "vardamaggarwal": "@santu.misra you guys should collaborate!\u2764\ufe0f\u2764\ufe0f\u2764\ufe0f", "iam.unableto.can": "Hahahaha\ud83d\udc4c\ud83c\udffb\ud83d\ude02", "amandeepvirk87": "@insta.rav.08 LOL", "deekumar9124": "\u2764\ufe0f", "haughty_temoin": "Apt for uh", "whatsbuzzingmissbee": "@yashikarohiira I\u2019m getting you this!!", "flying_diba": "@pallavi_richa249 @pragati_149 Tmlogo k liye banwa du kya?", "kidrauhl.forever.26": "@vasu_2812 DAMMNNNNN", "aashimaseedhar": "@bhawnaarora wanttt thisdd", "dhaarna_srivastava": "\ud83d\ude0d\ud83d\ude0d\ud83d\ude0d\ud83d\ude0d\ud83d\ude0d t-shirts. Bhiii plz @mallikadua", "sheena_anees": "@neon__god perfect necklace doesn't exis....", "vasu.tar.anand": "Hahaha!!!! Price plsss \ud83c\udfc3\ud83c\udfc3\ud83d\ude1d\ud83d\ude1d", "tanu_chawla_ahuja": "I want it these \ud83d\ude02\ud83d\ude0d", "bhawna__sharma": "@mr_samarth \ud83d\ude02", "palpaldilkepass": "Dua Pipa \"New Jewls\"", "ankita.0601": "@bhagatshital found a birthday gift for you \ud83e\udd2d\ud83e\udd2d", "omgitsvidhi": "U are one", "annoyingly_happie": "Hahhahaha u are next level bro \ud83d\ude02\ud83d\ude02\ud83d\ude02 jeeo hazaro saal beauty", "devikachopra0204": "@drpallavipatil @azzzbeh for us", "baklaaavaaa": "I\u2019m getting you this @saloni126", "da_baddesttttt": "Want \ud83d\udc9e", "saum245": "@jasleen.chawla144 this is what we gift each other next! U r the best \u0915\u0941\u0924\u094d\u0924\u0940 in my lyf \ud83d\ude18\ud83d\ude18\ud83d\ude18", "pritash_": "Baahhh\ud83d\ude02\ud83d\ude02\ud83d\ude02", "home_and_much_more": "Shaikhashu3", "puja_johri": "I have similar ( it says my name though)", "deepali12": "@yamini.tamrakar", "foodiesince96": "Can\u2019t wait \ud83d\ude0d", "nushkochar": "YAAASSSSS", "__s_ii_m__": "Seriously \ud83e\udd23\ud83e\udd23", "ashima_colorsnglitters\nVerified": "Verified", "shalinni1": "Luv it \u2764\ufe0f\u2764\ufe0f", "truptiunawane": "@siddhisurange_ we both should get this\ud83d\udd25", "makeuped_._": "Omg\ud83d\ude02 I want that", "manish8909": "Hahahahaha", "smitabudhia": "@drishti0694 shall we buy one?", "shweta.r.bhatnagar": "@akritigupta0695 we need this", "bhatia06nupur": "@mahima.kohli you want? \ud83d\ude02\ud83d\udd25\ud83d\ude3b", "saloni_gaunekar": "@dwittygoan", "pinkfreud93": "@jyotisingh1988 dila de ye.", "sujummapotato": "@priyanka.menyangbo yesto lagaera hinnu parla jasto chha", "rohina_nerdydevi": "OOOOOF \ud83e\udd70\ud83d\udc4a\ud83c\udffc\u2764\ufe0f", "mizmodgal": "Whoa!", "an.upma": "WANT WANT WANT!!", "kukreti_jayati": "\ud83d\ude0d\ud83d\ude0d\ud83d\ude0d", "ishagera7": "@ramya2888", "prakruthivarma": "Yes!!", "its_gunikaur": "\ud83d\udd25\ud83d\udd25\ud83d\udd25\ud83d\udd25\ud83d\udd25", "tamanna.chandak": "@kanchan This one for you babe\ud83d\ude02", "sheoran5715": "@_sarika1312_ didi is a geniusss\ud83d\ude0d", "monz.s.s": "Perfect", "simrann.ahuja": "Waiting\ud83d\udd25\ud83d\udd25\ud83d\udd25\ud83d\udd25\ud83d\udd25\ud83d\udd25\ud83d\udd25", "srish_shenanigans": "@tanisha.9 found your perfect birthday gift.\ud83d\udda4", "sonyaaayodhya\nVerified": "Verified", "paramsgram": "\ud83d\ude02\ud83d\ude02\ud83d\ude02", "a.nany.a_": "WHENNNNNN", "imtiazansari14": "\ud83d\ude0d\ud83d\udd25", "rubycheema": "Oh yeah \ud83d\ude4c\ud83d\ude4c", "chaaaima": "I think I\u2019ll buy this for you @mehkashi01", "instamanees": "@chwlageetu_geet", "sanaaakbarkhan": "@shamika_h @akneerude", "sapnasv89": "\u092c\u093f\u0902\u0926\u0940 \u0915\u0939\u093e\u0901 \u0917\u092f\u0940 #\u0915\u0941\u0902\u0924\u0940", "theweirdanaa": "Verry kyaut", "jannatsorathia": "Haha...best \ud83d\ude4c", "zishita": "\ud83d\ude02\ud83d\ude02\ud83d\ude02\ud83d\ude02", "pshaichedelic": "Bas isi ki kami thi zindagi mein..", "bhan_gram": "Oh YAAAAS! \ud83d\ude4c\ud83c\udffb", "arch5lyf": "@vaishnavii_matad wanttttt", "urvashiraseen": "Woah \ud83d\udd25\ud83d\ude0b\ud83d\ude0d", "anckitaa": "\u2764\ufe0f\u2665\ufe0f\u2665\ufe0f\u2665\ufe0f\u2764\ufe0f", "monmon_2890": "OMG DIDI..this is super cool!!! \ud83d\ude0d", "__saaaakshiiii__": "Yayyyy", "callmi_ak": "\ud83e\udd23\ud83d\ude02\ud83e\udd23\ud83d\ude02", "nanniiiiiii_": "@hitakshiiii buying this for us", "king.kumkum1": "Meko chahiye ye \ud83d\ude0b\u2764\u2764", "neharawat_o1": "@nishthasharrma I\u2019ll buy this for you \ud83d\ude02", "sherryshroff\nVerified": "Verified", "duaabha": "\ud83e\udd23 Too good \ud83d\udc4c\ud83c\udffb\ud83d\udc4c\ud83c\udffb", "neha_g_speaks": "OMG \ud83d\ude3b", "shabaaaa_": "@karanpreetx you have to buy this for yourself.", "pitturepafect": "This is kyaut Didi \u2763\ufe0f\ud83c\udf38", "julyissue_online": "\ud83d\ude0d\ud83d\udd25", "runnergirlinthekitchen": "Omg!!!", "apurvaahmalik": "@juhi_kapoor can youuu see \ud83d\ude02\ud83d\ude02\ud83d\ude02\ud83d\ude02\ud83d\ude02\ud83d\ude02\ud83d\ude02", "chaa.biskoot": "Kameeni\ud83d\ude02", "prachiya26": "I need this!", "dr_arshi_": "Lol!!!! Queen you are!! \ud83d\ude04\ud83d\udc95\ud83d\udc95", "sakinadawood": "@tassuzakir getting this for you", "vanshita_19": "@ridhimakumar06 want", "linkinthebioo": "Bhow bhow", "thebrownbox10": "Hahaha..too good", "shivi21": "\ud83d\udc4c\ud83c\udffb\ud83d\udc4c\ud83c\udffb", "ayesha__oo7": "Kamine \ud83d\ude02\ud83d\ude02\ud83d\ude02\ud83d\ude02", "vaishali_uma_singh": "@belle_southern_17 I will gift you this \ud83d\ude48\ud83d\ude02", "mail2saif_ali": "Hottie", "makeupbynandiniadvani": "Wow!", "ennkay.beetoons": "Mennu ni pata aahi main v lainaaaaa\ud83d\ude02\ud83d\ude02\ud83d\ude02 bitchie vibes tho", "jain.shreya.09": "@mallika1821 shud I buy it for u", "blunder_account": "Kutiya jyada sahi Lagta waise \ud83d\ude02\ud83d\ude02\ud83d\ude02", "medpreet": "@sunflowersandbullshit HAVE TO GET ME A KUTTI NECKLACE", "aaditi2290": "\ud83d\ude02", "sarwhinyyy": "@jnvi_rajesh get me thisss", "chalchhaiyachhaiya": "@__gazal__shaikh Waaaant", "krystal_glimmer_life": "@roopydhingra", "_aishwariyaa": "@ritikapandey28", "discover_saumya": "So cool didi..i love it..\u2764", "priyanka18021990": "\ud83d\udc4c\ud83d\udc4c", "ayena_mg": "I see a kutti group being made with @mallikadua @srishtipatch @kushakapila And @spill_the_sass \ud83d\ude0d\ud83d\ude02", "meenalbhanushali": "Whattt a wowwww\ud83d\ude0d\ud83d\ude0d", "mishikakhithani": "@shevonne.almeida @prekundnani", "sere.tonin": "\ud83d\ude0d", "bigfoodiemani": "@poodhawan \ud83d\udc4c\ud83d\udc4c\ud83d\udc95\ud83d\udc95", "shreyabhardwaj346": "Fuck\ud83d\ude02\ud83d\ude02\ud83d\ude02\ud83d\ude02\ud83d\ude02", "happilyforyou": "Shags didi this is whattewow", "galaxy_starfire": "Fits you", "nehasdharmesh": "Bitchy didi", "sumati._": "Yes yes yessssssss\ud83d\ude48", "purnimaadhikari1": "Chi re kuch bhi kya!!!!!!\u00a1", "creative_side_of_sahil": "@simran.harchandani \ud83d\ude02\ud83d\ude02now i know what I'm gonna gift you \ud83d\ude02\ud83d\ude02\ud83d\ude02\ud83d\ude02", "vwebie": "Kutti \ud83d\ude02 where did you get that @mallikadua ?", "aradhanaburagohain_official": "\ud83e\udd23\ud83e\udd23\ud83e\udd23\ud83d\ude02\ud83d\ude02I died", "obsessedbyfuschia": "Omg that's Epic!", "poorvisrivastav": "@cheetarahere you start with Dogin \ud83d\ude02\ud83d\ude02\ud83d\ude02\ud83d\ude02", "gehnakundra": "@rushalikler birthday gift found", "hasnaoui202": "Niccc\ud83d\ude0d\ud83d\ude0d\ud83d\ude0d", "chhavi_basra": "That lip bite though", "muskankawat": "Whatta wow \ud83d\udc95\ud83d\ude18", "sugar_crayon": "Mehenga maal bhi khareedne tayar hu ab me. Life badi #Kutti cheez hai! \ud83e\udd13", "_abhilasha_25_": "\ud83d\udd25\ud83d\udd25\ud83d\udd25\ud83d\udd25\ud83d\udd25", "thepakhisinha": "Didi..... I am dying to buy this collection\ud83d\ude2d", "meriiimarziii": "@gulaaabjaamun", "jayesh_rath": "\ud83d\udd25\ud83d\udd25\ud83d\udd25 he tuzhya saathi.", "kkkanakmittal": "Want this !!\ud83d\ude0d", "terpsichoreramya": "\ud83d\ude02\ud83d\ude02\ud83d\ude02\ud83d\ude02\ud83d\ude02\ud83d\ude02 Omg", "since_01.01.01": "@neelambari._ naughty stuff", "rhhheeeeee": "@slooooo_ @shreyayayayayaya Let's get this", "sparkhi_99": "Arreyyy kyaa baat \ud83d\ude02\u2764\ufe0f #Kyaut", "adiiii.pvt": "Wow\u2764\ufe0f", "kokitheblog": "\u0932\u0935 \u0907\u091f !! \u2764\ufe0f", "shivi_official1": "@agrawalshivu i really want to gift u this \ud83e\udd23\ud83e\udd23\ud83e\udd23", "duaananya": "Boss\u2665\ufe0f", "monikaverma4_hair": "U r the spirit janwar gurl.... love this bitch one\ud83d\ude02\ud83d\ude18\ud83d\udc4c", "neha_radio": "@adityanarayan007 Yeh launch hone ke baad main tujhe gift karungi.", "srishtipatch\nVerified": "Verified", "mehak.arora.15": "Lovinnnn it \u2764\ufe0f", "rajesh_kandhari": "Hehe\ud83d\ude1a", "panditanisha": "@saini.dipti \ud83d\ude02", "mousamsemily": "Lobhely lip colou didi...ki bolbo", "anuxxza": "@___kanishkaaa ae kutte vali chain tu hi pehn", "sandhu_keerti": "@neha.gehlot", "mozezsingh\nVerified": "Verified", "himanshi.himmi": "@username_kya_krna_h oh gosh this is for u meri kuttia", "duskymiss": "@meharpannu dila do", "introvert_quoran": "Galat likha.... Mam u r cutie", "subhashdtta": "\ud83d\udc2f\ud83d\udc2f\ud83d\udc05\ud83d\udc05", "shaheenkapadia8": "@shyreen.batliwala ill bring u a chain like this", "saranology": "Omggg", "pratyush.the.king": "Fast follow me just now follow back \ud83d\udd25\ud83d\udd25\ud83d\udd25\u2764\ufe0f\u2764\ufe0f\u2764\ufe0f", "niyaaatiii_": "@kashveeee", "jacobsigram": "Aayeeee \ud83d\ude08\ud83d\ude08\ud83d\ude02@ishu001_100", "pipabella\nVerified": "Verified", "shru_negi702": "\ud83d\udd25\ud83d\ude02\ud83d\ude02", "____hemantsingh____": "@rheasharma02 get one\ud83d\udd25"}