{"yolonda_j": "Yo. This. @abarberwill", "livingwaterisfree": "Culture 0% \ud83d\ude02\ud83d\ude02\ud83d\ude02\ud83d\ude02", "marina.marqueza": "@whitefeministbarbie", "maroonedalienprincess": "The ingredients \ud83d\ude02\ud83d\ude02\ud83d\ude02\ud83d\ude02", "exploringdora04": "@la_luna_chingona24", "markohflowers": "@yesicalli LOLOL", "hijade13serpiente": "@chunti_princess @deusa_linaa \ud83d\ude02", "sammiey_": "@yesicalli culture 0 \ud83d\ude02\ud83d\ude02 acurate!", "lareenolastname": "@veromo11 @joshx414 @_wiscago lolz", "dr_quisible": "@lareenolastname \ud83d\ude02 I'm showing this to dr Harris!", "drumkingshawn": "@demoizelle ;)", "veromo11": "@lareenolastname lmao", "croiizzant": "@dearprudence_x what we wuss talking bout lol look at culture", "des_pier_ta_te": "@aye_eddieka", "rendaj_": "@rerekalel", "wonderwomn": "Powerful", "la_consentida_gr24": "@tomtomjei", "deusa_linaa": "@yesicalli \ud83d\ude05\ud83d\ude05\ud83d\ude05", "demoizelle": "@drumkingshawn \ud83d\ude4a", "espiadri": "@espmarce @ohkaylulu @eraesp", "emkeas": "Zero culture", "kimmortaltheartist": "@descolonizar_amor", "sad_salvi": "@\ud83d\ude02\ud83d\ude02"}