{"dbdamonsta": "U eat ass\ud83e\udd14", "_tracedat": "Just sent an email !", "k1ng1128": "I swear to God I thought it was a microphone \ud83e\udd23\ud83e\udd23\ud83e\udd23\ud83e\udd23", "giorgio_mbha": "\ud83d\ude0b\ud83c\udf51", "viaratalent": "\ud83e\udd2d over the \ud83d\udc56 on a \u201cshow me the catFAX mileage\ud83d\ude40\u201d tho !!!! Fakkkkkkk!!! \ud83d\udc40That is seems toooo powerful.., like you need OSHA and an industrial permit to even use it!", "supreme998586": "Nice", "goddess_nevina": "Is it loud?", "runrowliftrepeat": "#greatshirttt", "gal.pacino": "are you making more of these shirts? i need one", "lildannyg": "@raquelsavage where did you get that shirt ?! It\u2019s rad", "allaboutme_el": "You don\u2019t say", "the_real_scott_swells": "doesn't everybody??", "shawn_wingfield": "@secretxplorations", "waltonb56": "I eat pussy and love it\ud83d\udcaf", "_annyma": "@half.queen", "truelifemediaatl": "@yourpleasureprincipal", "mikecharby": "@curls_n_camo", "monee_mitch": "@be_youtiful_hazel \ud83d\ude02\ud83d\ude02\ud83d\ude02", "_dipped_in_gold": "@kerajes_visions", "sneakerking_38": "@raquelsavage how can I buy that shirt \ud83d\udc4d\ud83c\udffd", "jeffleach753": "U can eat my ass anytime\ud83d\ude0d\ud83d\ude0d\ud83d\ude0d\u2764\ufe0f\u2764\ufe0f\u2764\ufe0f\u2764\ufe0f", "jonesybackdown": "@freezetracks thugluv when @gwells356 eating \ud83c\udf7d", "risamora": "@scorpio_heaux needs to get me one of these!!!", "lissaaires": "Me too \ud83d\ude4b\ud83c\udffb\u200d\u2640\ufe0f", "aquafare": "Is this one waterproof? \ud83c\udf0a\ud83d\udca6\ud83d\udca7", "tessaxellex": "Biiiihhhh it\u2019s pretty too! Idk HOW you forgot to mention that lol", "d3ad.stvr": "Pause\ud83d\udc80", "williamvcrouch": "You are just too sexy.", "kavellkeir": "A must have !", "honeydupain": "Welp. Guess I know what I\u2019m ordering.", "kessbomb": "@bmonz101", "fit_of_rage": "Makes me want it even more! Sounds awesome", "effvee_": "I NEED THAT SHIRT! \ud83d\ude0d", "hannahmichulltz": "@tiny_tits6969 @crispy_legs @hey_katrail @spicy.wench For Taylor", "eastside_kevy": "This shirt come in men's?", "catesqrophe": "@oldmanbasel", "foxc_fine9": "Blow your coochie out the water... well damn. We ain\u2019t been truly living", "d_uno_": "@raquelsavage do you have a podcast? If so what is the name of it so I can tune in.", "jaylovers_": "Oooo really", "naicha7": "@xlswagga just reminded me of you \ud83d\ude02\ud83d\ude02\ud83d\ude02\ud83d\ude02\ud83d\ude02", "makeupmagx": "I tried it in the tub and the tub shook.", "my_own__entity": "\ud83d\ude10", "nina.haines": "ICONIC WOW \ud83d\ude0d\ud83d\ude0d\ud83d\ude2d", "rihannamadonnajohanna": "I need the toy AND the shirt in my life!", "robertbynes8455": "@raquelsavage I need that shirt in a 6xl please \ud83d\ude09 can we make this possible.", "ama.rhosa": "I know what I'm getting myself for Christmas! \u263a\u263a\u263a", "cbgxo": "Youre back!!", "unboundbabes\nVerified": "Verified", "lozanocasanova": "\ud83d\udd25\ud83d\udd25\ud83d\udd25", "alextheok_": "You\u2019re back!!!\ud83d\udc99", "fertile_resistance08": "\ud83d\udd25!!!", "burgundyanteater": "Nice shirt", "kremedelakitty": "@j.starsuperchrist big need"}